Workbook

Sheet Sold
AD1: =COUNT(Sold[DATE])
B2: LEASE NO. | C2: AGENCY | D2: TYPE | E2: INTEREST | F2: ADDRESS | G2: CITY | H2: STATE | I2: LAND | J2: BUILT | K2: SF LEASED | L2: RBA | M2: GOV OCCP | N2: GROSS | O2: GROSS/SF | P2: NOI | Q2: NET/SF | R2: COM | S2: EXP | T2: TERMN | U2: TERM | V2: FIRM | W2: EXPENSES | X2: BUMPS | Y2: RENEWAL OPTIONS | Z2: SOLD PRICE | AA2: SOLD/SF | AB2: SOLD CAP | AC2: ZCF | AD2: DATE | AE2: SELLER | AF2: L. BROKER | AG2: BUYER | AH2: Bstate | AI2: Type2 | AJ2: P. BROKER | AK2: DEVELOPER | AL2: INITIAL PRICE | AM2: INITIAL CAP | AN2: % of Int Ach | AO2: LAST PRICE | AP2: LAST CAP | AQ2: BID-ASK SPREAD | AR2: PRICE CHG | AS2: ON MARKET | AT2: DOM

Sheet Ownership
B2: LEASE NO. | C2: NEW | D2: LOC. CODE | E2: Date | F2: RENEWED | G2: AGENCY | H2: Rep. Agency | I2: Reduce TF | J2: INTEREST | K2: ADDRESS | L2: CITY | M2: STATE | N2: LAND | O2: BUILT | P2: BTS | Q2: SF LEASED | R2: RBA | S2: OCCP | T2: GSA OCCP | U2: GROSS | V2: GROSS/SF | W2: FUTURE/SF | X2: CAGR | Y2: NOI | Z2: NET/SF | AA2: Tenure at Com | AB2: #ofRenewals | AC2: ORG. OCC. | AD2: COM | AE2: EXP | AF2: TERMN | AG2: Last | AH2: Term | AI2: Firm | AJ2: T-Rem | AK2: F-Rem | AL2: EXPS | AM2: OPTS | AN2: EST SIZE | AO2: RECORDED | AP2: TRUE OWNER | AQ2: LAST LL | AR2: COMP | AS2: DEVELOPER

Sheet Inventory
B2: Lease Num | C2: Old | D2: Location Code | E2: City | F2: County | G2: Address | H2: State | I2: ZipCode | J2: Latitude | K2: Longitude | L2: Field Office Name | M2: Cen Bus Unit Ind | N2: Lease Effective | O2: Lease Expiration | P2: Termination Right Date | Q2: Latest Action affecting Term | R2: Fully Serviced | S2: Lease Agreement RSF | T2: Lease Structured Parking | U2: Lease Surface parking | V2: Percent Building | W2: Current Annual Rent | X2: Percent Office | Y2: Percent Warehouse | Z2: Percent Special | AA2: Renewal Option Term left | AB2: Renewal Options Left | AC2: Lessor name

Sheet All Charts
BE1: =AVERAGE(BE24:BE145) | BJ1: =AVERAGE(BJ24:BJ340) | BM1: =AVERAGE(BM24:BM364) | BN1: =AVERAGE(BN24:BN364)
B2: Quarter | C2: Date | D2: Transactions (ttm) | E2: Average Deal Size (ttm) | F2: Monthly Volume | G2: Transaction Volume (ttm) | H2: Trans. Vol. (ttm) | I2: yoy Change (%) | J2: Upper Quartile Cap Rate (ttm) | K2: Lower Quartile Cap Rate (ttm) | L2: Average Cap Rate (ttm) | M2: NM Average Cap (ttm) | N2: Non-NM Average Cap (ttm) | O2: 10+ Year Cap (ttm) | P2: 6 to 10 Year Cap (ttm) | Q2: Less than 5 Year Cap (ttm) | R2: Outside Firm Term (ttm) | S2: Private Volume (ttm) | T2: Public Listed/REIT Volume (ttm) | U2: Cross-Border Volume (ttm) | V2: Institutional Volume (ttm) | W2: Federal Cap | X2: State Cap | Y2: Municipal Cap | Z2: Private Count (ttm) | AA2: Public Listed/REIT Count (ttm) | AB2: Cross-Border Count (ttm) | AC2: Institutional Count (ttm) | AD2: DOM | AE2: % of Ask | AF2: Last Ask | AG2: Bid-Ask Spread | AH2: 10-Year Treasury Yield | AI2: Low Assumed Loan Constant | AJ2: High Assumed Loan Constant | AK2: Price Change (ttm) | AL2: 8+ Year Firm Ask (ttm) | AM2: 8+ Year Firm Price Change (ttm) | AN2: First Generation Lease Commencements (ttm) | AO2: Renewed Leases (ttm) | AP2: Succeeding/Superseding Leases (ttm) | AQ2: Expired Leases (ttm) | AR2: Terminated Leases (ttm) | AS2: Net Change (ttm) | AT2: Total Current Leases (ttm) | AU2: Leases Extended (ttm) | AV2: Footprint Reduced (ttm) | AW2: Leases Expired (ttm) | AX2: Leases Up for Renewal (ttm) | AY2: Leases In Firm Term (ttm) | AZ2: Leases Outside Firm (ttm) | BA2: Leases Terminated (ttm) | BB2: Renewal Rent/SF | BC2: Upper Quartile | BD2: Lower Quartile | BE2: Average Renewal Rent CAGR | BF2: Tenure at Renewal | BG2: Average Lease Term | BH2: Renewal Count | BI2: Avg. Rent | BJ2: Valuation Index | BK2: YOY Change (%)2 | BL2: Expenses PSF (ttm) | BM2: Cash Return Index | BN2: Leveraged Return Index | BO2: CPI
B3: Q2-2025 | C3: 45838 | D3: =COUNTIFS(Sold[DATE],">"&EDATE(Charts[[#This Row],[Date]],-12),Sold[DATE],"<="&Charts[[#This Row],[Date]]) | E3: =AVERAGEIFS(Sold[SOLD PRICE],Sold[DATE],">"&EDATE(Charts[[#This Row],[Date]],-12),Sold[DATE],"<="&Charts[[#This Row],[Date]]) | F3: =SUMIFS(Sold[SOLD PRICE],Sold[DATE],">"&EDATE(Charts[[#This Row],[Date]],-1),Sold[DATE],"<="&Charts[[#This Row],[Date]]) | G3: =SUMIFS(Sold[SOLD PRICE],Sold[DATE],">"&EDATE(Charts[[#This Row],[Date]],-12),Sold[DATE],"<="&Charts[[#This Row],[Date]]) | H3: =Charts[[#This Row],[Average Deal Size (ttm)]]*Charts[[#This Row],[Transactions (ttm)]] | I3: =(Charts[[#This Row],[Trans. Vol. (ttm)]]-H15)/H15 | J3: {=PERCENTILE(IF(Sold[DATE]>EDATE(Charts[[#This Row],[Date]],-12),IF(Sold[DATE]<=Charts[[#This Row],[Date]],IF(Sold[SOLD CAP]<>"",Sold[SOLD CAP]))),0.75)} | K3: {=PERCENTILE(IF(Sold[DATE]>EDATE(Charts[[#This Row],[Date]],-12),IF(Sold[DATE]<=Charts[[#This Row],[Date]],IF(Sold[SOLD CAP]<>"",Sold[SOLD CAP]))),0.25)} | L3: =AVERAGEIFS(Sold[SOLD CAP],Sold[DATE],">"&EDATE(Charts[[#This Row],[Date]],-12),Sold[DATE],"<="&Charts[[#This Row],[Date]]) | M3: =IFERROR(AVERAGEIFS(Sold[SOLD CAP],Sold[DATE],">"&EDATE(Charts[[#This Row],[Date]],-12),Sold[DATE],"<="&Charts[[#This Row],[Date]],Sold[L. BROKER],"*sjc*",Sold[SOLD CAP],"<=.09"),M8) | N3: =IF(Charts[[#This Row],[Average Cap Rate (ttm)]]>(AVERAGEIFS(Sold[SOLD CAP],Sold[L. BROKER],"<>*",Sold[L. BROKER],"<>*sjc*",Sold[DATE],">"&EDATE(Charts[[#This Row],[Date]],-12),Sold[DATE],"<="&Charts[[#This Row],[Date]])),Charts[[#This Row],[Average Cap Rate (ttm)]],AVERAGEIFS(Sold[SOLD CAP],Sold[L. BROKER],"<>*",Sold[L. BROKER],"<>*sjc*",Sold[DATE],">"&EDATE(Charts[[#This Row],[Date]],-12),Sold[DATE],"<="&Charts[[#This Row],[Date]])) | O3: =IFERROR(AVERAGEIFS(Sold[SOLD CAP],Sold[FIRM],">="&10,Sold[DATE],">"&EDATE(Charts[[#This Row],[Date]],-12),Sold[DATE],"<="&Charts[[#This Row],[Date]]),#REF!) | P3: =IFERROR(AVERAGEIFS(Sold[SOLD CAP],Sold[FIRM],">="&6,Sold[FIRM],"<"&10,Sold[DATE],">"&EDATE(Charts[[#This Row],[Date]],-12),Sold[DATE],"<="&Charts[[#This Row],[Date]]),#REF!) | Q3: =IFERROR(AVERAGEIFS(Sold[SOLD CAP],Sold[FIRM],"<"&6,Sold[DATE],">"&EDATE(Charts[[#This Row],[Date]],-12),Sold[DATE],"<="&Charts[[#This Row],[Date]]),#REF!) | R3: =IFERROR(AVERAGEIFS(Sold[SOLD CAP],Sold[FIRM],"<"&0.5,Sold[DATE],">"&EDATE(Charts[[#This Row],[Date]],-12),Sold[DATE],"<="&Charts[[#This Row],[Date]],Sold[FIRM],"<>"&" "),#REF!) | S3: =SUMIFS(Sold[SOLD PRICE],Sold[Type2],"*Private*",Sold[DATE],">"&EDATE(Charts[[#This Row],[Date]],-12),Sold[DATE],"<="&Charts[[#This Row],[Date]]) | T3: =SUMIFS(Sold[SOLD PRICE],Sold[Type2],"*REIT*",Sold[DATE],">"&EDATE(Charts[[#This Row],[Date]],-12),Sold[DATE],"<="&Charts[[#This Row],[Date]]) | U3: =SUMIFS(Sold[SOLD PRICE],Sold[Type2],"*Cross*",Sold[DATE],">"&EDATE(Charts[[#This Row],[Date]],-12),Sold[DATE],"<="&Charts[[#This Row],[Date]]) | V3: =SUMIFS(Sold[SOLD PRICE],Sold[Type2],"*Institutional*",Sold[DATE],">"&EDATE(Charts[[#This Row],[Date]],-12),Sold[DATE],"<="&Charts[[#This Row],[Date]]) | W3: =AVERAGEIFS(Sold[SOLD CAP],Sold[DATE],">"&EDATE(Charts[[#This Row],[Date]],-12),Sold[DATE],"<="&Charts[[#This Row],[Date]],Sold[TYPE],"*Federal*") | X3: =AVERAGEIFS(Sold[SOLD CAP],Sold[DATE],">"&EDATE(Charts[[#This Row],[Date]],-12),Sold[DATE],"<="&Charts[[#This Row],[Date]],Sold[TYPE],"*State*") | Y3: =IFERROR(AVERAGEIFS(Sold[SOLD CAP],Sold[DATE],">"&EDATE(Charts[[#This Row],[Date]],-12),Sold[DATE],"<="&Charts[[#This Row],[Date]],Sold[TYPE],"*Municipal*"),Y8) | Z3: =COUNTIFS(Sold[Type2],"*Private*",Sold[DATE],">"&EDATE(Charts[[#This Row],[Date]],-12),Sold[DATE],"<="&Charts[[#This Row],[Date]]) | AA3: =COUNTIFS(Sold[Type2],"*REIT*",Sold[DATE],">"&EDATE(Charts[[#This Row],[Date]],-12),Sold[DATE],"<="&Charts[[#This Row],[Date]]) | AB3: =COUNTIFS(Sold[Type2],"*Cross*",Sold[DATE],">"&EDATE(Charts[[#This Row],[Date]],-12),Sold[DATE],"<="&Charts[[#This Row],[Date]]) | AC3: =COUNTIFS(Sold[Type2],"*Institutional*",Sold[DATE],">"&EDATE(Charts[[#This Row],[Date]],-12),Sold[DATE],"<="&Charts[[#This Row],[Date]]) | AD3: =AVERAGEIFS(Sold[DOM],Sold[DATE],">"&EDATE(Charts[[#This Row],[Date]],-12),Sold[DATE],"<="&Charts[[#This Row],[Date]]) | AE3: =AVERAGEIFS(Sold[% of Int Ach],Sold[DATE],"<="&C3,Sold[DATE],">"&EDATE(Charts[[#This Row],[Date]],-12)) | AF3: =AVERAGEIFS(Sold[LAST CAP],Sold[DATE],"<="&Charts[[#This Row],[Date]],Sold[DATE],">"&EDATE(Charts[[#This Row],[Date]],-12)) | AG3: =AVERAGEIFS(Sold[BID-ASK SPREAD],Sold[DATE],"<="&Charts[[#This Row],[Date]],Sold[DATE],">"&EDATE(Charts[[#This Row],[Date]],-12)) | AH3: 0.04177 | AI3: =PMT((Charts[[#This Row],[10-Year Treasury Yield]]+0.018)/12,360,-1,0)*12 | AJ3: =PMT((Charts[[#This Row],[10-Year Treasury Yield]]+0.022)/12,360,-1,0)*12 | AK3: =COUNTIFS(Sold[PRICE CHG],"*Yes*",Sold[DATE],">"&EDATE(Charts[[#This Row],[Date]],-12),Sold[DATE],"<="&Charts[[#This Row],[Date]])/COUNTIFS(Sold[DOM],"<>",Sold[DATE],">"&EDATE(Charts[[#This Row],[Date]],-12),Sold[DATE],"<="&Charts[[#This Row],[Date]]) | AL3: =AVERAGEIFS(Sold[LAST CAP],Sold[DATE],">"&EDATE(Charts[[#This Row],[Date]],-12),Sold[DATE],"<="&Charts[[#This Row],[Date]],Sold[FIRM],">="&7.5) | AM3: =COUNTIFS(Sold[PRICE CHG],"*Yes*",Sold[DATE],">"&EDATE(Charts[[#This Row],[Date]],-12),Sold[DATE],"<="&Charts[[#This Row],[Date]],Sold[FIRM],">="&7.5)/COUNTIFS(Sold[DOM],"<>",Sold[DATE],">"&EDATE(Charts[[#This Row],[Date]],-12),Sold[DATE],"<="&Charts[[#This Row],[Date]],Sold[FIRM],">="&7.5) | AN3: =COUNTIFS(Ownership[COM],">"&EDATE(Charts[[#This Row],[Date]],-12),Ownership[COM],"<="&Charts[[#This Row],[Date]],Ownership[Last],"New") | AO3: =(COUNTIFS(Ownership[COM],">"&EDATE(Charts[[#This Row],[Date]],-12),Ownership[COM],"<="&Charts[[#This Row],[Date]],Ownership[Last],"*replacing*"))+(COUNTIFS(Ownership[COM],">"&EDATE(Charts[[#This Row],[Date]],-12),Ownership[COM],"<="&Charts[[#This Row],[Date]],Ownership[Last],"*renew*"))+(COUNTIFS(Ownership[COM],">"&EDATE(Charts[[#This Row],[Date]],-12),Ownership[COM],"<="&Charts[[#This Row],[Date]],Ownership[Last],"*exten*")) | AP3: =(COUNTIFS(Ownership[COM],">"&EDATE(Charts[[#This Row],[Date]],-12),Ownership[COM],"<="&Charts[[#This Row],[Date]],Ownership[Last],"*succeed*"))+(COUNTIFS(Ownership[COM],">"&EDATE(Charts[[#This Row],[Date]],-12),Ownership[COM],"<="&Charts[[#This Row],[Date]],Ownership[Last],"*superse*")) | AQ3: =-COUNTIFS(Ownership[EXP],"<="&Charts[[#This Row],[Date]],Ownership[EXP],">"&EDATE(Charts[[#This Row],[Date]],-12),Ownership[NEW],"#N/A") | AR3: =Charts[[#This Row],[Expired Leases (ttm)]]+COUNTIFS(Ownership[EXP],"<="&Charts[[#This Row],[Date]],Ownership[EXP],">"&EDATE(Charts[[#This Row],[Date]],-12),Ownership[NEW],"#N/A",Ownership[TERMN],"<="&EDATE(Charts[[#This Row],[Date]],-12)) | AS3: =Charts[[#This Row],[First Generation Lease Commencements (ttm)]]+Charts[[#This Row],[Renewed Leases (ttm)]]+Charts[[#This Row],[Succeeding/Superseding Leases (ttm)]]+Charts[[#This Row],[Expired Leases (ttm)]]+Charts[[#This Row],[Terminated Leases (ttm)]] | AT3: =(COUNTIFS(Ownership[EXP],">="&Charts[[#This Row],[Date]],Ownership[COM],"<="&Charts[[#This Row],[Date]],Ownership[NEW],"<>*#N/A*")) | AU3: =COUNTIFS(Ownership[RENEWED],"*Yes*",Ownership[Date],">"&EDATE(Charts[[#This Row],[Date]],-12),Ownership[Date],"<="&Charts[[#This Row],[Date]]) | AV3: =COUNTIFS(Ownership[RENEWED],"*Reduced*",Ownership[Date],">"&EDATE(Charts[[#This Row],[Date]],-12),Ownership[Date],"<="&Charts[[#This Row],[Date]]) | AW3: =COUNTIFS(Ownership[RENEWED],"*No*",Ownership[Date],">"&EDATE(Charts[[#This Row],[Date]],-12),Ownership[Date],"<="&Charts[[#This Row],[Date]]) | AX3: =SUM(Charts[[#This Row],[Leases Extended (ttm)]:[Leases Expired (ttm)]]) | AY3: =Charts[[#This Row],[Total Current Leases (ttm)]]-Charts[[#This Row],[Leases Outside Firm (ttm)]] | AZ3: =COUNTIFS(Ownership[TERMN],"<"&C3,Ownership[EXP],">"&C3) | BA3: =-Charts[[#This Row],[Terminated Leases (ttm)]]/Charts[[#This Row],[Leases Outside Firm (ttm)]] | BB3: =AVERAGEIFS(Ownership[FUTURE/SF],Ownership[FUTURE/SF],"<>"&0,Ownership[EXP],">="&EDATE(Charts[[#This Row],[Date]],-12),Ownership[EXP],"<="&Charts[[#This Row],[Date]]) | BC3: {=PERCENTILE(IF(Ownership[EXP]>EDATE(Charts[[#This Row],[Date]],-12),IF(Ownership[EXP]<=Charts[[#This Row],[Date]],IF(Ownership[CAGR]<>0,Ownership[CAGR]))),0.75)} | BD3: {=PERCENTILE(IF(Ownership[EXP]>EDATE(Charts[[#This Row],[Date]],-12),IF(Ownership[EXP]<=Charts[[#This Row],[Date]],IF(Ownership[CAGR]<>0,Ownership[CAGR]))),0.25)} | BE3: =AVERAGEIFS(Ownership[CAGR],Ownership[CAGR],"<>"&0,Ownership[EXP],">="&EDATE(Charts[[#This Row],[Date]],-12),Ownership[EXP],"<="&Charts[[#This Row],[Date]],Ownership[Term],">="&3) | BF3: =AVERAGEIFS(Ownership[Tenure at Com],Ownership[COM],">"&EDATE(Charts[[#This Row],[Date]],-12),Ownership[COM],"<="&Charts[[#This Row],[Date]]) | BG3: =AVERAGEIFS(Ownership[Term],Ownership[COM],">"&EDATE(Charts[[#This Row],[Date]],-12),Ownership[COM],"<="&Charts[[#This Row],[Date]]) | BH3: =AVERAGEIFS(Ownership['#ofRenewals],Ownership[COM],"<="&Charts[[#This Row],[Date]],Ownership[COM],">"&EDATE(Charts[[#This Row],[Date]],-12)) | BI3: =AVERAGE(AVERAGEIFS(Ownership[GROSS/SF],Ownership[EXP],"<="&Charts[[#This Row],[Date]],Ownership[Term],">="&0),AVERAGEIFS(Sold[GROSS/SF],Sold[EXP],"<="&Charts[[#This Row],[Date]],Sold[TERM],">="&0)) | BJ3: =(Charts[[#This Row],[Avg. Rent]]-Charts[[#This Row],[Expenses PSF (ttm)]])/Charts[[#This Row],[Average Cap Rate (ttm)]] | BK3: =(Charts[[#This Row],[Valuation Index]]-BJ15)/BJ15 | BL3: =AVERAGEIFS(Sold[GROSS/SF],Sold[DATE],"<="&Charts[[#This Row],[Date]],Sold[DATE],">"&EDATE(Charts[[#This Row],[Date]],-12),Sold[GROSS/SF],"<>"&0,Sold[NET/SF],"<>"&0)-AVERAGEIFS(Sold[NET/SF],Sold[DATE],"<="&Charts[[#This Row],[Date]],Sold[DATE],">"&EDATE(Charts[[#This Row],[Date]],-12),Sold[GROSS/SF],"<>"&0,Sold[NET/SF],"<>"&0) | BM3: =(Charts[[#This Row],[Lower Quartile Cap Rate (ttm)]]*0.25)+(Charts[[#This Row],[Average Cap Rate (ttm)]]*0.5)+(Charts[[#This Row],[Upper Quartile Cap Rate (ttm)]]*0.25) | BN3: =(1-((1/Charts[[#This Row],[Cash Return Index]])*0.5)*AVERAGE(Charts[[#This Row],[Low Assumed Loan Constant]:[High Assumed Loan Constant]]))/((1/Charts[[#This Row],[Cash Return Index]])*0.5)
C4: 45808 | D4: =COUNTIFS(Sold[DATE],">"&EDATE(Charts[[#This Row],[Date]],-12),Sold[DATE],"<="&Charts[[#This Row],[Date]]) | E4: =AVERAGEIFS(Sold[SOLD PRICE],Sold[DATE],">"&EDATE(Charts[[#This Row],[Date]],-12),Sold[DATE],"<="&Charts[[#This Row],[Date]]) | F4: =SUMIFS(Sold[SOLD PRICE],Sold[DATE],">"&EDATE(Charts[[#This Row],[Date]],-1),Sold[DATE],"<="&Charts[[#This Row],[Date]]) | G4: =SUMIFS(Sold[SOLD PRICE],Sold[DATE],">"&EDATE(Charts[[#This Row],[Date]],-12),Sold[DATE],"<="&Charts[[#This Row],[Date]]) | H4: =Charts[[#This Row],[Average Deal Size (ttm)]]*Charts[[#This Row],[Transactions (ttm)]] | I4: =(Charts[[#This Row],[Trans. Vol. (ttm)]]-H16)/H16 | J4: {=PERCENTILE(IF(Sold[DATE]>EDATE(Charts[[#This Row],[Date]],-12),IF(Sold[DATE]<=Charts[[#This Row],[Date]],IF(Sold[SOLD CAP]<>"",Sold[SOLD CAP]))),0.75)} | K4: {=PERCENTILE(IF(Sold[DATE]>EDATE(Charts[[#This Row],[Date]],-12),IF(Sold[DATE]<=Charts[[#This Row],[Date]],IF(Sold[SOLD CAP]<>"",Sold[SOLD CAP]))),0.25)} | L4: =AVERAGEIFS(Sold[SOLD CAP],Sold[DATE],">"&EDATE(Charts[[#This Row],[Date]],-12),Sold[DATE],"<="&Charts[[#This Row],[Date]]) | M4: =IFERROR(AVERAGEIFS(Sold[SOLD CAP],Sold[DATE],">"&EDATE(Charts[[#This Row],[Date]],-12),Sold[DATE],"<="&Charts[[#This Row],[Date]],Sold[L. BROKER],"*sjc*",Sold[SOLD CAP],"<=.09"),M9) | N4: =IF(Charts[[#This Row],[Average Cap Rate (ttm)]]>(AVERAGEIFS(Sold[SOLD CAP],Sold[L. BROKER],"<>*",Sold[L. BROKER],"<>*sjc*",Sold[DATE],">"&EDATE(Charts[[#This Row],[Date]],-12),Sold[DATE],"<="&Charts[[#This Row],[Date]])),Charts[[#This Row],[Average Cap Rate (ttm)]],AVERAGEIFS(Sold[SOLD CAP],Sold[L. BROKER],"<>*",Sold[L. BROKER],"<>*sjc*",Sold[DATE],">"&EDATE(Charts[[#This Row],[Date]],-12),Sold[DATE],"<="&Charts[[#This Row],[Date]])) | O4: =IFERROR(AVERAGEIFS(Sold[SOLD CAP],Sold[FIRM],">="&10,Sold[DATE],">"&EDATE(Charts[[#This Row],[Date]],-12),Sold[DATE],"<="&Charts[[#This Row],[Date]]),#REF!) | P4: =IFERROR(AVERAGEIFS(Sold[SOLD CAP],Sold[FIRM],">="&6,Sold[FIRM],"<"&10,Sold[DATE],">"&EDATE(Charts[[#This Row],[Date]],-12),Sold[DATE],"<="&Charts[[#This Row],[Date]]),#REF!) | Q4: =IFERROR(AVERAGEIFS(Sold[SOLD CAP],Sold[FIRM],"<"&6,Sold[DATE],">"&EDATE(Charts[[#This Row],[Date]],-12),Sold[DATE],"<="&Charts[[#This Row],[Date]]),#REF!) | R4: =IFERROR(AVERAGEIFS(Sold[SOLD CAP],Sold[FIRM],"<"&0.5,Sold[DATE],">"&EDATE(Charts[[#This Row],[Date]],-12),Sold[DATE],"<="&Charts[[#This Row],[Date]],Sold[FIRM],"<>"&" "),#REF!) | S4: =SUMIFS(Sold[SOLD PRICE],Sold[Type2],"*Private*",Sold[DATE],">"&EDATE(Charts[[#This Row],[Date]],-12),Sold[DATE],"<="&Charts[[#This Row],[Date]]) | T4: =SUMIFS(Sold[SOLD PRICE],Sold[Type2],"*REIT*",Sold[DATE],">"&EDATE(Charts[[#This Row],[Date]],-12),Sold[DATE],"<="&Charts[[#This Row],[Date]]) | U4: =SUMIFS(Sold[SOLD PRICE],Sold[Type2],"*Cross*",Sold[DATE],">"&EDATE(Charts[[#This Row],[Date]],-12),Sold[DATE],"<="&Charts[[#This Row],[Date]]) | V4: =SUMIFS(Sold[SOLD PRICE],Sold[Type2],"*Institutional*",Sold[DATE],">"&EDATE(Charts[[#This Row],[Date]],-12),Sold[DATE],"<="&Charts[[#This Row],[Date]]) | W4: =AVERAGEIFS(Sold[SOLD CAP],Sold[DATE],">"&EDATE(Charts[[#This Row],[Date]],-12),Sold[DATE],"<="&Charts[[#This Row],[Date]],Sold[TYPE],"*Federal*") | X4: =AVERAGEIFS(Sold[SOLD CAP],Sold[DATE],">"&EDATE(Charts[[#This Row],[Date]],-12),Sold[DATE],"<="&Charts[[#This Row],[Date]],Sold[TYPE],"*State*") | Y4: =IFERROR(AVERAGEIFS(Sold[SOLD CAP],Sold[DATE],">"&EDATE(Charts[[#This Row],[Date]],-12),Sold[DATE],"<="&Charts[[#This Row],[Date]],Sold[TYPE],"*Municipal*"),Y9) | Z4: =COUNTIFS(Sold[Type2],"*Private*",Sold[DATE],">"&EDATE(Charts[[#This Row],[Date]],-12),Sold[DATE],"<="&Charts[[#This Row],[Date]]) | AA4: =COUNTIFS(Sold[Type2],"*REIT*",Sold[DATE],">"&EDATE(Charts[[#This Row],[Date]],-12),Sold[DATE],"<="&Charts[[#This Row],[Date]]) | AB4: =COUNTIFS(Sold[Type2],"*Cross*",Sold[DATE],">"&EDATE(Charts[[#This Row],[Date]],-12),Sold[DATE],"<="&Charts[[#This Row],[Date]]) | AC4: =COUNTIFS(Sold[Type2],"*Institutional*",Sold[DATE],">"&EDATE(Charts[[#This Row],[Date]],-12),Sold[DATE],"<="&Charts[[#This Row],[Date]]) | AD4: =AVERAGEIFS(Sold[DOM],Sold[DATE],">"&EDATE(Charts[[#This Row],[Date]],-12),Sold[DATE],"<="&Charts[[#This Row],[Date]]) | AE4: =AVERAGEIFS(Sold[% of Int Ach],Sold[DATE],"<="&C4,Sold[DATE],">"&EDATE(Charts[[#This Row],[Date]],-12)) | AF4: =AVERAGEIFS(Sold[LAST CAP],Sold[DATE],"<="&Charts[[#This Row],[Date]],Sold[DATE],">"&EDATE(Charts[[#This Row],[Date]],-12)) | AG4: =AVERAGEIFS(Sold[BID-ASK SPREAD],Sold[DATE],"<="&Charts[[#This Row],[Date]],Sold[DATE],">"&EDATE(Charts[[#This Row],[Date]],-12)) | AH4: 0.04177 | AI4: =PMT((Charts[[#This Row],[10-Year Treasury Yield]]+0.018)/12,360,-1,0)*12 | AJ4: =PMT((Charts[[#This Row],[10-Year Treasury Yield]]+0.022)/12,360,-1,0)*12 | AK4: =COUNTIFS(Sold[PRICE CHG],"*Yes*",Sold[DATE],">"&EDATE(Charts[[#This Row],[Date]],-12),Sold[DATE],"<="&Charts[[#This Row],[Date]])/COUNTIFS(Sold[DOM],"<>",Sold[DATE],">"&EDATE(Charts[[#This Row],[Date]],-12),Sold[DATE],"<="&Charts[[#This Row],[Date]]) | AL4: =AVERAGEIFS(Sold[LAST CAP],Sold[DATE],">"&EDATE(Charts[[#This Row],[Date]],-12),Sold[DATE],"<="&Charts[[#This Row],[Date]],Sold[FIRM],">="&7.5) | AM4: =COUNTIFS(Sold[PRICE CHG],"*Yes*",Sold[DATE],">"&EDATE(Charts[[#This Row],[Date]],-12),Sold[DATE],"<="&Charts[[#This Row],[Date]],Sold[FIRM],">="&7.5)/COUNTIFS(Sold[DOM],"<>",Sold[DATE],">"&EDATE(Charts[[#This Row],[Date]],-12),Sold[DATE],"<="&Charts[[#This Row],[Date]],Sold[FIRM],">="&7.5) | AN4: =COUNTIFS(Ownership[COM],">"&EDATE(Charts[[#This Row],[Date]],-12),Ownership[COM],"<="&Charts[[#This Row],[Date]],Ownership[Last],"New") | AO4: =(COUNTIFS(Ownership[COM],">"&EDATE(Charts[[#This Row],[Date]],-12),Ownership[COM],"<="&Charts[[#This Row],[Date]],Ownership[Last],"*replacing*"))+(COUNTIFS(Ownership[COM],">"&EDATE(Charts[[#This Row],[Date]],-12),Ownership[COM],"<="&Charts[[#This Row],[Date]],Ownership[Last],"*renew*"))+(COUNTIFS(Ownership[COM],">"&EDATE(Charts[[#This Row],[Date]],-12),Ownership[COM],"<="&Charts[[#This Row],[Date]],Ownership[Last],"*exten*")) | AP4: =(COUNTIFS(Ownership[COM],">"&EDATE(Charts[[#This Row],[Date]],-12),Ownership[COM],"<="&Charts[[#This Row],[Date]],Ownership[Last],"*succeed*"))+(COUNTIFS(Ownership[COM],">"&EDATE(Charts[[#This Row],[Date]],-12),Ownership[COM],"<="&Charts[[#This Row],[Date]],Ownership[Last],"*superse*")) | AQ4: =-COUNTIFS(Ownership[EXP],"<="&Charts[[#This Row],[Date]],Ownership[EXP],">"&EDATE(Charts[[#This Row],[Date]],-12),Ownership[NEW],"#N/A") | AR4: =Charts[[#This Row],[Expired Leases (ttm)]]+COUNTIFS(Ownership[EXP],"<="&Charts[[#This Row],[Date]],Ownership[EXP],">"&EDATE(Charts[[#This Row],[Date]],-12),Ownership[NEW],"#N/A",Ownership[TERMN],"<="&EDATE(Charts[[#This Row],[Date]],-12)) | AS4: =Charts[[#This Row],[First Generation Lease Commencements (ttm)]]+Charts[[#This Row],[Renewed Leases (ttm)]]+Charts[[#This Row],[Succeeding/Superseding Leases (ttm)]]+Charts[[#This Row],[Expired Leases (ttm)]]+Charts[[#This Row],[Terminated Leases (ttm)]] | AT4: =(COUNTIFS(Ownership[EXP],">="&Charts[[#This Row],[Date]],Ownership[COM],"<="&Charts[[#This Row],[Date]],Ownership[NEW],"<>*#N/A*")) | AU4: =COUNTIFS(Ownership[RENEWED],"*Yes*",Ownership[Date],">"&EDATE(Charts[[#This Row],[Date]],-12),Ownership[Date],"<="&Charts[[#This Row],[Date]]) | AV4: =COUNTIFS(Ownership[RENEWED],"*Reduced*",Ownership[Date],">"&EDATE(Charts[[#This Row],[Date]],-12),Ownership[Date],"<="&Charts[[#This Row],[Date]]) | AW4: =COUNTIFS(Ownership[RENEWED],"*No*",Ownership[Date],">"&EDATE(Charts[[#This Row],[Date]],-12),Ownership[Date],"<="&Charts[[#This Row],[Date]]) | AX4: =SUM(Charts[[#This Row],[Leases Extended (ttm)]:[Leases Expired (ttm)]]) | AY4: =Charts[[#This Row],[Total Current Leases (ttm)]]-Charts[[#This Row],[Leases Outside Firm (ttm)]] | AZ4: =COUNTIFS(Ownership[TERMN],"<"&C4,Ownership[EXP],">"&C4) | BA4: =-Charts[[#This Row],[Terminated Leases (ttm)]]/Charts[[#This Row],[Leases Outside Firm (ttm)]] | BB4: =AVERAGEIFS(Ownership[FUTURE/SF],Ownership[FUTURE/SF],"<>"&0,Ownership[EXP],">="&EDATE(Charts[[#This Row],[Date]],-12),Ownership[EXP],"<="&Charts[[#This Row],[Date]]) | BC4: {=PERCENTILE(IF(Ownership[EXP]>EDATE(Charts[[#This Row],[Date]],-12),IF(Ownership[EXP]<=Charts[[#This Row],[Date]],IF(Ownership[CAGR]<>0,Ownership[CAGR]))),0.75)} | BD4: {=PERCENTILE(IF(Ownership[EXP]>EDATE(Charts[[#This Row],[Date]],-12),IF(Ownership[EXP]<=Charts[[#This Row],[Date]],IF(Ownership[CAGR]<>0,Ownership[CAGR]))),0.25)} | BE4: =AVERAGEIFS(Ownership[CAGR],Ownership[CAGR],"<>"&0,Ownership[EXP],">="&EDATE(Charts[[#This Row],[Date]],-12),Ownership[EXP],"<="&Charts[[#This Row],[Date]],Ownership[Term],">="&3) | BF4: =AVERAGEIFS(Ownership[Tenure at Com],Ownership[COM],">"&EDATE(Charts[[#This Row],[Date]],-12),Ownership[COM],"<="&Charts[[#This Row],[Date]]) | BG4: =AVERAGEIFS(Ownership[Term],Ownership[COM],">"&EDATE(Charts[[#This Row],[Date]],-12),Ownership[COM],"<="&Charts[[#This Row],[Date]]) | BH4: =AVERAGEIFS(Ownership['#ofRenewals],Ownership[COM],"<="&Charts[[#This Row],[Date]],Ownership[COM],">"&EDATE(Charts[[#This Row],[Date]],-12)) | BI4: =AVERAGE(AVERAGEIFS(Ownership[GROSS/SF],Ownership[EXP],"<="&Charts[[#This Row],[Date]],Ownership[Term],">="&0),AVERAGEIFS(Sold[GROSS/SF],Sold[EXP],"<="&Charts[[#This Row],[Date]],Sold[TERM],">="&0)) | BJ4: =(Charts[[#This Row],[Avg. Rent]]-Charts[[#This Row],[Expenses PSF (ttm)]])/Charts[[#This Row],[Average Cap Rate (ttm)]] | BK4: =(Charts[[#This Row],[Valuation Index]]-BJ16)/BJ16 | BL4: =AVERAGEIFS(Sold[GROSS/SF],Sold[DATE],"<="&Charts[[#This Row],[Date]],Sold[DATE],">"&EDATE(Charts[[#This Row],[Date]],-12),Sold[GROSS/SF],"<>"&0,Sold[NET/SF],"<>"&0)-AVERAGEIFS(Sold[NET/SF],Sold[DATE],"<="&Charts[[#This Row],[Date]],Sold[DATE],">"&EDATE(Charts[[#This Row],[Date]],-12),Sold[GROSS/SF],"<>"&0,Sold[NET/SF],"<>"&0) | BM4: =(Charts[[#This Row],[Lower Quartile Cap Rate (ttm)]]*0.25)+(Charts[[#This Row],[Average Cap Rate (ttm)]]*0.5)+(Charts[[#This Row],[Upper Quartile Cap Rate (ttm)]]*0.25) | BN4: =(1-((1/Charts[[#This Row],[Cash Return Index]])*0.5)*AVERAGE(Charts[[#This Row],[Low Assumed Loan Constant]:[High Assumed Loan Constant]]))/((1/Charts[[#This Row],[Cash Return Index]])*0.5)

Sheet SSA Charts
D1: =AVERAGE(SSACharts[Transactions (ttm)])
B2: Quarter | C2: Date | D2: Transactions (ttm) | E2: Average Deal Size (ttm) | F2: Monthly Volume | G2: Transaction Volume (ttm) | H2: Trans. Vol. (ttm) | I2: y-o-y Change (%) | J2: Upper Quartile Cap Rate (ttm) | K2: Lower Quartile Cap Rate (ttm) | L2: Average Cap Rate (ttm) | M2: SJC Average Cap (ttm) | N2: Non-SJC Average Cap (ttm) | O2: 3+ Year Cap (ttm) | P2: 0 to 3 Year Cap (ttm) | Q2: 2.5 to 5 Year Cap (ttm) | R2: Less than 2.5 Year Cap (ttm) | S2: Outside Firm Term (ttm) | T2: Private Volume (ttm) | U2: Public Listed/REIT Volume (ttm) | V2: Cross-Border Volume (ttm) | W2: Institutional Volume (ttm) | X2: Private Count (ttm) | Y2: Public Listed/REIT Count (ttm) | Z2: Cross-Border Count (ttm) | AA2: Institutional Count (ttm) | AB2: DOM | AC2: % of Ask | AD2: Last Ask | AE2: Bid-Ask Spread | AF2: 10-Year Treasury Yield | AG2: Low Assumed Loan Constant | AH2: High Assumed Loan Constant | AI2: Price Change (ttm) | AJ2: 3+ Year Firm Ask (ttm) | AK2: 3+ Year Firm Price Change (ttm) | AL2: First Generation Lease Commencements (ttm) | AM2: Renewed Leases (ttm) | AN2: Succeeding/Superseding Leases (ttm) | AO2: Expired Leases (ttm) | AP2: Terminated Leases (ttm) | AQ2: Net Change (ttm) | AR2: Total Current Leases (ttm) | AS2: Leases Extended (ttm) | AT2: Footprint Reduced (ttm) | AU2: Leases Expired (ttm) | AV2: Leases Up for Renewal (ttm) | AW2: Leases In Firm Term (ttm) | AX2: Leases Outside Firm (ttm) | AY2: Leases Terminated (ttm)
B3: Q4-2022 | C3: 44926 | D3: =COUNTIFS(Sold[DATE],">"&EDATE(SSACharts[[#This Row],[Date]],-12),Sold[DATE],"<="&SSACharts[[#This Row],[Date]],Sold[AGENCY],"*SSA*") | E3: =AVERAGEIFS(Sold[SOLD PRICE],Sold[DATE],">"&EDATE(SSACharts[[#This Row],[Date]],-12),Sold[DATE],"<="&SSACharts[[#This Row],[Date]],Sold[AGENCY],"*ssa*",Sold[SOLD PRICE],"<"&25000000) | F3: =SUMIFS(Sold[SOLD PRICE],Sold[DATE],">"&EDATE(SSACharts[[#This Row],[Date]],-1),Sold[DATE],"<="&SSACharts[[#This Row],[Date]],Sold[AGENCY],"*ssa*") | G3: =SUMIFS(Sold[SOLD PRICE],Sold[DATE],">"&EDATE(SSACharts[[#This Row],[Date]],-12),Sold[DATE],"<="&SSACharts[[#This Row],[Date]],Sold[AGENCY],"*ssa*") | H3: =SSACharts[[#This Row],[Transactions (ttm)]]*SSACharts[[#This Row],[Average Deal Size (ttm)]] | I3: =(SSACharts[[#This Row],[Trans. Vol. (ttm)]]-H14)/H14 | J3: {=PERCENTILE(IF(Sold[DATE]>EDATE(SSACharts[[#This Row],[Date]],-12),IF(Sold[DATE]<=SSACharts[[#This Row],[Date]],IF(Sold[SOLD CAP]<>"",IF(Sold[AGENCY]="ssa",Sold[SOLD CAP])))),0.75)} | K3: {=PERCENTILE(IF(Sold[DATE]>EDATE(SSACharts[[#This Row],[Date]],-12),IF(Sold[DATE]<=SSACharts[[#This Row],[Date]],IF(Sold[SOLD CAP]<>"",IF(Sold[AGENCY]="ssa",Sold[SOLD CAP])))),0.25)} | L3: =AVERAGEIFS(Sold[SOLD CAP],Sold[DATE],">"&EDATE(SSACharts[[#This Row],[Date]],-12),Sold[DATE],"<="&SSACharts[[#This Row],[Date]],Sold[AGENCY],"*ssa*") | M3: =IFERROR(AVERAGE(AVERAGEIFS(Sold[SOLD CAP],Sold[DATE],">"&EDATE(SSACharts[[#This Row],[Date]],-12),Sold[DATE],"<="&SSACharts[[#This Row],[Date]],Sold[L. BROKER],"*sjc*",Sold[AGENCY],"*ssa*"),IFERROR(AVERAGEIFS(Sold[SOLD CAP],Sold[DATE],">"&EDATE(SSACharts[[#This Row],[Date]],-12),Sold[DATE],"<="&SSACharts[[#This Row],[Date]],Sold[P. BROKER],"*sjc*",Sold[AGENCY],"*ssa*"),M2)),M2) | N3: =IFERROR(AVERAGEIFS(Sold[SOLD CAP],Sold[L. BROKER],"<>*sjc*",Sold[L. BROKER],"<>0",Sold[P. BROKER],"<>*sjc*",Sold[DATE],">"&EDATE(SSACharts[[#This Row],[Date]],-12),Sold[DATE],"<="&SSACharts[[#This Row],[Date]],Sold[AGENCY],"*ssa*",Sold[SOLD PRICE],"<="&10000000),N2) | O3: =IFERROR(AVERAGEIFS(Sold[SOLD CAP],Sold[FIRM],">="&3,Sold[DATE],">"&EDATE(SSACharts[[#This Row],[Date]],-12),Sold[DATE],"<="&SSACharts[[#This Row],[Date]],Sold[AGENCY],"*ssa*"),O2) | P3: =IFERROR(AVERAGEIFS(Sold[SOLD CAP],Sold[FIRM],">="&0,Sold[FIRM],"<"&3,Sold[DATE],">"&EDATE(SSACharts[[#This Row],[Date]],-12),Sold[DATE],"<="&SSACharts[[#This Row],[Date]],Sold[AGENCY],"*ssa*"),P2) | Q3: =IFERROR(AVERAGEIFS(Sold[SOLD CAP],Sold[FIRM],">="&2.5,Sold[FIRM],"<"&5,Sold[DATE],">"&EDATE(SSACharts[[#This Row],[Date]],-12),Sold[DATE],"<="&SSACharts[[#This Row],[Date]],Sold[AGENCY],"*ssa*"),Q2) | R3: =IFERROR(AVERAGEIFS(Sold[SOLD CAP],Sold[FIRM],"<"&2.5,Sold[FIRM],">="&0,Sold[DATE],">"&EDATE(SSACharts[[#This Row],[Date]],-12),Sold[DATE],"<="&SSACharts[[#This Row],[Date]],Sold[AGENCY],"*ssa*"),R2) | S3: =IFERROR(AVERAGEIFS(Sold[SOLD CAP],Sold[FIRM],"<"&0,Sold[FIRM],"<>"&" ",Sold[DATE],">"&EDATE(SSACharts[[#This Row],[Date]],-12),Sold[DATE],"<="&SSACharts[[#This Row],[Date]],Sold[AGENCY],"*ssa*"),R2) | AB3: =IFERROR(AVERAGEIFS(Sold[DOM],Sold[DATE],">"&EDATE(SSACharts[[#This Row],[Date]],-12),Sold[DATE],"<="&SSACharts[[#This Row],[Date]],Sold[AGENCY],"*ssa*"),AB2) | AC3: =IFERROR(AVERAGEIFS(Sold[% of Int Ach],Sold[DATE],"<="&C3,Sold[DATE],">"&EDATE(SSACharts[[#This Row],[Date]],-12),Sold[AGENCY],"*ssa*"),AC2) | AD3: =IFERROR(AVERAGEIFS(Sold[LAST CAP],Sold[DATE],"<="&SSACharts[[#This Row],[Date]],Sold[DATE],">"&EDATE(SSACharts[[#This Row],[Date]],-12),Sold[AGENCY],"*ssa*"),AD2) | AE3: =IFERROR(AVERAGEIFS(Sold[BID-ASK SPREAD],Sold[DATE],"<="&SSACharts[[#This Row],[Date]],Sold[DATE],">"&EDATE(SSACharts[[#This Row],[Date]],-12),Sold[AGENCY],"*ssa*"),AE2) | AF3: 0.0353 | AG3: =PMT((SSACharts[[#This Row],[10-Year Treasury Yield]]+0.018)/12,360,-1,0)*12 | AH3: =PMT((SSACharts[[#This Row],[10-Year Treasury Yield]]+0.022)/12,360,-1,0)*12 | AI3: =IFERROR(COUNTIFS(Sold[PRICE CHG],"*Yes*",Sold[DATE],">"&EDATE(SSACharts[[#This Row],[Date]],-12),Sold[DATE],"<="&SSACharts[[#This Row],[Date]],Sold[AGENCY],"*ssa*")/COUNTIFS(Sold[DOM],"<>",Sold[DATE],">"&EDATE(SSACharts[[#This Row],[Date]],-12),Sold[DATE],"<="&SSACharts[[#This Row],[Date]],Sold[AGENCY],"*ssa*"),AI2) | AJ3: =IFERROR(AVERAGEIFS(Sold[LAST CAP],Sold[DATE],">"&EDATE(SSACharts[[#This Row],[Date]],-12),Sold[DATE],"<="&SSACharts[[#This Row],[Date]],Sold[FIRM],">="&3,Sold[AGENCY],"*ssa*"),AJ2) | AK3: =IFERROR(COUNTIFS(Sold[PRICE CHG],"*Yes*",Sold[DATE],">"&EDATE(SSACharts[[#This Row],[Date]],-12),Sold[DATE],"<="&SSACharts[[#This Row],[Date]],Sold[FIRM],">="&3,Sold[AGENCY],"*ssa*")/COUNTIFS(Sold[DOM],"<>",Sold[DATE],">"&EDATE(SSACharts[[#This Row],[Date]],-12),Sold[DATE],"<="&SSACharts[[#This Row],[Date]],Sold[FIRM],">="&3,Sold[AGENCY],"*ssa*"),AK2) | BD3: 5 - GOVT COUNT & DEAL SIZE CHART
C4: 44895 | D4: =COUNTIFS(Sold[DATE],">"&EDATE(SSACharts[[#This Row],[Date]],-12),Sold[DATE],"<="&SSACharts[[#This Row],[Date]],Sold[AGENCY],"*SSA*") | E4: =AVERAGEIFS(Sold[SOLD PRICE],Sold[DATE],">"&EDATE(SSACharts[[#This Row],[Date]],-12),Sold[DATE],"<="&SSACharts[[#This Row],[Date]],Sold[AGENCY],"*ssa*",Sold[SOLD PRICE],"<"&25000000) | F4: =SUMIFS(Sold[SOLD PRICE],Sold[DATE],">"&EDATE(SSACharts[[#This Row],[Date]],-1),Sold[DATE],"<="&SSACharts[[#This Row],[Date]],Sold[AGENCY],"*ssa*") | G4: =SUMIFS(Sold[SOLD PRICE],Sold[DATE],">"&EDATE(SSACharts[[#This Row],[Date]],-12),Sold[DATE],"<="&SSACharts[[#This Row],[Date]],Sold[AGENCY],"*ssa*") | H4: =SSACharts[[#This Row],[Transactions (ttm)]]*SSACharts[[#This Row],[Average Deal Size (ttm)]] | I4: =(SSACharts[[#This Row],[Trans. Vol. (ttm)]]-H15)/H15 | J4: {=PERCENTILE(IF(Sold[DATE]>EDATE(SSACharts[[#This Row],[Date]],-12),IF(Sold[DATE]<=SSACharts[[#This Row],[Date]],IF(Sold[SOLD CAP]<>"",IF(Sold[AGENCY]="ssa",Sold[SOLD CAP])))),0.75)} | K4: {=PERCENTILE(IF(Sold[DATE]>EDATE(SSACharts[[#This Row],[Date]],-12),IF(Sold[DATE]<=SSACharts[[#This Row],[Date]],IF(Sold[SOLD CAP]<>"",IF(Sold[AGENCY]="ssa",Sold[SOLD CAP])))),0.25)} | L4: =AVERAGEIFS(Sold[SOLD CAP],Sold[DATE],">"&EDATE(SSACharts[[#This Row],[Date]],-12),Sold[DATE],"<="&SSACharts[[#This Row],[Date]],Sold[AGENCY],"*ssa*") | M4: =IFERROR(AVERAGE(AVERAGEIFS(Sold[SOLD CAP],Sold[DATE],">"&EDATE(SSACharts[[#This Row],[Date]],-12),Sold[DATE],"<="&SSACharts[[#This Row],[Date]],Sold[L. BROKER],"*sjc*",Sold[AGENCY],"*ssa*"),IFERROR(AVERAGEIFS(Sold[SOLD CAP],Sold[DATE],">"&EDATE(SSACharts[[#This Row],[Date]],-12),Sold[DATE],"<="&SSACharts[[#This Row],[Date]],Sold[P. BROKER],"*sjc*",Sold[AGENCY],"*ssa*"),M3)),M3) | N4: =IFERROR(AVERAGEIFS(Sold[SOLD CAP],Sold[L. BROKER],"<>*sjc*",Sold[L. BROKER],"<>0",Sold[P. BROKER],"<>*sjc*",Sold[DATE],">"&EDATE(SSACharts[[#This Row],[Date]],-12),Sold[DATE],"<="&SSACharts[[#This Row],[Date]],Sold[AGENCY],"*ssa*",Sold[SOLD PRICE],"<="&10000000),N3) | O4: =IFERROR(AVERAGEIFS(Sold[SOLD CAP],Sold[FIRM],">="&3,Sold[DATE],">"&EDATE(SSACharts[[#This Row],[Date]],-12),Sold[DATE],"<="&SSACharts[[#This Row],[Date]],Sold[AGENCY],"*ssa*"),O3) | P4: =IFERROR(AVERAGEIFS(Sold[SOLD CAP],Sold[FIRM],">="&0,Sold[FIRM],"<"&3,Sold[DATE],">"&EDATE(SSACharts[[#This Row],[Date]],-12),Sold[DATE],"<="&SSACharts[[#This Row],[Date]],Sold[AGENCY],"*ssa*"),P3) | Q4: =IFERROR(AVERAGEIFS(Sold[SOLD CAP],Sold[FIRM],">="&2.5,Sold[FIRM],"<"&5,Sold[DATE],">"&EDATE(SSACharts[[#This Row],[Date]],-12),Sold[DATE],"<="&SSACharts[[#This Row],[Date]],Sold[AGENCY],"*ssa*"),Q3) | R4: =IFERROR(AVERAGEIFS(Sold[SOLD CAP],Sold[FIRM],"<"&2.5,Sold[FIRM],">="&0,Sold[DATE],">"&EDATE(SSACharts[[#This Row],[Date]],-12),Sold[DATE],"<="&SSACharts[[#This Row],[Date]],Sold[AGENCY],"*ssa*"),R3) | S4: =IFERROR(AVERAGEIFS(Sold[SOLD CAP],Sold[FIRM],"<"&0,Sold[FIRM],"<>"&" ",Sold[DATE],">"&EDATE(SSACharts[[#This Row],[Date]],-12),Sold[DATE],"<="&SSACharts[[#This Row],[Date]],Sold[AGENCY],"*ssa*"),R3) | AB4: =IFERROR(AVERAGEIFS(Sold[DOM],Sold[DATE],">"&EDATE(SSACharts[[#This Row],[Date]],-12),Sold[DATE],"<="&SSACharts[[#This Row],[Date]],Sold[AGENCY],"*ssa*"),AB3) | AC4: =IFERROR(AVERAGEIFS(Sold[% of Int Ach],Sold[DATE],"<="&C4,Sold[DATE],">"&EDATE(SSACharts[[#This Row],[Date]],-12),Sold[AGENCY],"*ssa*"),AC3) | AD4: =IFERROR(AVERAGEIFS(Sold[LAST CAP],Sold[DATE],"<="&SSACharts[[#This Row],[Date]],Sold[DATE],">"&EDATE(SSACharts[[#This Row],[Date]],-12),Sold[AGENCY],"*ssa*"),AD3) | AE4: =IFERROR(AVERAGEIFS(Sold[BID-ASK SPREAD],Sold[DATE],"<="&SSACharts[[#This Row],[Date]],Sold[DATE],">"&EDATE(SSACharts[[#This Row],[Date]],-12),Sold[AGENCY],"*ssa*"),AE3) | AF4: 0.0387 | AG4: =PMT((SSACharts[[#This Row],[10-Year Treasury Yield]]+0.018)/12,360,-1,0)*12 | AH4: =PMT((SSACharts[[#This Row],[10-Year Treasury Yield]]+0.022)/12,360,-1,0)*12 | AI4: =IFERROR(COUNTIFS(Sold[PRICE CHG],"*Yes*",Sold[DATE],">"&EDATE(SSACharts[[#This Row],[Date]],-12),Sold[DATE],"<="&SSACharts[[#This Row],[Date]],Sold[AGENCY],"*ssa*")/COUNTIFS(Sold[DOM],"<>",Sold[DATE],">"&EDATE(SSACharts[[#This Row],[Date]],-12),Sold[DATE],"<="&SSACharts[[#This Row],[Date]],Sold[AGENCY],"*ssa*"),AI3) | AJ4: =IFERROR(AVERAGEIFS(Sold[LAST CAP],Sold[DATE],">"&EDATE(SSACharts[[#This Row],[Date]],-12),Sold[DATE],"<="&SSACharts[[#This Row],[Date]],Sold[FIRM],">="&3,Sold[AGENCY],"*ssa*"),AJ3) | AK4: =IFERROR(COUNTIFS(Sold[PRICE CHG],"*Yes*",Sold[DATE],">"&EDATE(SSACharts[[#This Row],[Date]],-12),Sold[DATE],"<="&SSACharts[[#This Row],[Date]],Sold[FIRM],">="&3,Sold[AGENCY],"*ssa*")/COUNTIFS(Sold[DOM],"<>",Sold[DATE],">"&EDATE(SSACharts[[#This Row],[Date]],-12),Sold[DATE],"<="&SSACharts[[#This Row],[Date]],Sold[FIRM],">="&3,Sold[AGENCY],"*ssa*"),AK3)

Sheet Rent Survey
G2: =SUM(F4:F36)/SUM(D4:D36) | H2: =SUM(C4:C36)/SUM(F4:F36)
B3: Year Built | C3: Sum of Rent | D3: Count of Rent | E3: Average Rents | F3: Sum of RBA | G3: Average RBA | H3: Average RPSF | I3: Upper Quartile Rent | J3: Lower Quartile Rent | K3: Median Rent PSF
B4: 2024 | C4: =SUMIFS(Sold[GROSS],Sold[BUILT],B4,Sold[GOV OCCP],">="&0.5)+SUMIFS(Ownership[GROSS],Ownership[BUILT],B4,Ownership[OCCP],">="&50) | D4: =COUNTIFS(Sold[GROSS],">"&0,Sold[BUILT],B4,Sold[GOV OCCP],">="&0.5)+COUNTIFS(Ownership[GROSS],">"&0,Ownership[BUILT],B4,Ownership[OCCP],">="&50) | E4: =C4/D4 | F4: =SUMIFS(Sold[RBA],Sold[BUILT],B4,Sold[GROSS],">"&0,Sold[GOV OCCP],">="&0.5)+SUMIFS(Ownership[SF LEASED],Ownership[BUILT],B4,Ownership[GROSS],">"&0,Ownership[OCCP],">="&50) | G4: =F4/D4 | H4: =C4/F4 | I4: {=PERCENTILE(IF(Sold[BUILT]=B4,Sold[GROSS/SF]),0.75)} | J4: {=PERCENTILE(IF(Sold[BUILT]=B4,Sold[GROSS/SF]),0.25)} | K4: {=MEDIAN(IF(Sold[BUILT]=B4,Sold[GROSS/SF]))} | M4: 15 - Rent by Year Built
B5: 2023 | C5: =SUMIFS(Sold[GROSS],Sold[BUILT],B5,Sold[GOV OCCP],">="&0.5)+SUMIFS(Ownership[GROSS],Ownership[BUILT],B5,Ownership[OCCP],">="&50) | D5: =COUNTIFS(Sold[GROSS],">"&0,Sold[BUILT],B5,Sold[GOV OCCP],">="&0.5)+COUNTIFS(Ownership[GROSS],">"&0,Ownership[BUILT],B5,Ownership[OCCP],">="&50) | E5: =C5/D5 | F5: =SUMIFS(Sold[RBA],Sold[BUILT],B5,Sold[GROSS],">"&0,Sold[GOV OCCP],">="&0.5)+SUMIFS(Ownership[SF LEASED],Ownership[BUILT],B5,Ownership[GROSS],">"&0,Ownership[OCCP],">="&50) | G5: =F5/D5 | H5: =C5/F5 | I5: {=PERCENTILE(IF(Sold[BUILT]=B5,Sold[GROSS/SF]),0.75)} | J5: {=PERCENTILE(IF(Sold[BUILT]=B5,Sold[GROSS/SF]),0.25)} | K5: {=MEDIAN(IF(Sold[BUILT]=B5,Sold[GROSS/SF]))}
B6: 2022 | C6: =SUMIFS(Sold[GROSS],Sold[BUILT],B6,Sold[GOV OCCP],">="&0.5)+SUMIFS(Ownership[GROSS],Ownership[BUILT],B6,Ownership[OCCP],">="&50) | D6: =COUNTIFS(Sold[GROSS],">"&0,Sold[BUILT],B6,Sold[GOV OCCP],">="&0.5)+COUNTIFS(Ownership[GROSS],">"&0,Ownership[BUILT],B6,Ownership[OCCP],">="&50) | E6: =C6/D6 | F6: =SUMIFS(Sold[RBA],Sold[BUILT],B6,Sold[GROSS],">"&0,Sold[GOV OCCP],">="&0.5)+SUMIFS(Ownership[SF LEASED],Ownership[BUILT],B6,Ownership[GROSS],">"&0,Ownership[OCCP],">="&50) | G6: =F6/D6 | H6: =C6/F6 | I6: {=PERCENTILE(IF(Sold[BUILT]=B6,Sold[GROSS/SF]),0.75)} | J6: {=PERCENTILE(IF(Sold[BUILT]=B6,Sold[GROSS/SF]),0.25)} | K6: {=MEDIAN(IF(Sold[BUILT]=B6,Sold[GROSS/SF]))}
B7: 2021 | C7: =SUMIFS(Sold[GROSS],Sold[BUILT],B7,Sold[GOV OCCP],">="&0.5)+SUMIFS(Ownership[GROSS],Ownership[BUILT],B7,Ownership[OCCP],">="&50) | D7: =COUNTIFS(Sold[GROSS],">"&0,Sold[BUILT],B7,Sold[GOV OCCP],">="&0.5)+COUNTIFS(Ownership[GROSS],">"&0,Ownership[BUILT],B7,Ownership[OCCP],">="&50) | E7: =C7/D7 | F7: =SUMIFS(Sold[RBA],Sold[BUILT],B7,Sold[GROSS],">"&0,Sold[GOV OCCP],">="&0.5)+SUMIFS(Ownership[SF LEASED],Ownership[BUILT],B7,Ownership[GROSS],">"&0,Ownership[OCCP],">="&50) | G7: =F7/D7 | H7: =C7/F7 | I7: {=PERCENTILE(IF(Sold[BUILT]=B7,Sold[GROSS/SF]),0.75)} | J7: {=PERCENTILE(IF(Sold[BUILT]=B7,Sold[GROSS/SF]),0.25)} | K7: {=MEDIAN(IF(Sold[BUILT]=B7,Sold[GROSS/SF]))}
B8: 2020 | C8: =SUMIFS(Sold[GROSS],Sold[BUILT],B8,Sold[GOV OCCP],">="&0.5)+SUMIFS(Ownership[GROSS],Ownership[BUILT],B8,Ownership[OCCP],">="&50) | D8: =COUNTIFS(Sold[GROSS],">"&0,Sold[BUILT],B8,Sold[GOV OCCP],">="&0.5)+COUNTIFS(Ownership[GROSS],">"&0,Ownership[BUILT],B8,Ownership[OCCP],">="&50) | E8: =C8/D8 | F8: =SUMIFS(Sold[RBA],Sold[BUILT],B8,Sold[GROSS],">"&0,Sold[GOV OCCP],">="&0.5)+SUMIFS(Ownership[SF LEASED],Ownership[BUILT],B8,Ownership[GROSS],">"&0,Ownership[OCCP],">="&50) | G8: =F8/D8 | H8: =C8/F8 | I8: {=PERCENTILE(IF(Sold[BUILT]=B8,Sold[GROSS/SF]),0.75)} | J8: {=PERCENTILE(IF(Sold[BUILT]=B8,Sold[GROSS/SF]),0.25)} | K8: {=MEDIAN(IF(Sold[BUILT]=B8,Sold[GROSS/SF]))}
B9: 2019 | C9: =SUMIFS(Sold[GROSS],Sold[BUILT],B9,Sold[GOV OCCP],">="&0.5)+SUMIFS(Ownership[GROSS],Ownership[BUILT],B9,Ownership[OCCP],">="&50) | D9: =COUNTIFS(Sold[GROSS],">"&0,Sold[BUILT],B9,Sold[GOV OCCP],">="&0.5)+COUNTIFS(Ownership[GROSS],">"&0,Ownership[BUILT],B9,Ownership[OCCP],">="&50) | E9: =C9/D9 | F9: =SUMIFS(Sold[RBA],Sold[BUILT],B9,Sold[GROSS],">"&0,Sold[GOV OCCP],">="&0.5)+SUMIFS(Ownership[SF LEASED],Ownership[BUILT],B9,Ownership[GROSS],">"&0,Ownership[OCCP],">="&50) | G9: =F9/D9 | H9: =C9/F9 | I9: {=PERCENTILE(IF(Sold[BUILT]=B9,Sold[GROSS/SF]),0.75)} | J9: {=PERCENTILE(IF(Sold[BUILT]=B9,Sold[GROSS/SF]),0.25)} | K9: {=MEDIAN(IF(Sold[BUILT]=B9,Sold[GROSS/SF]))}
B10: 2018 | C10: =SUMIFS(Sold[GROSS],Sold[BUILT],B10,Sold[GOV OCCP],">="&0.5)+SUMIFS(Ownership[GROSS],Ownership[BUILT],B10,Ownership[OCCP],">="&50) | D10: =COUNTIFS(Sold[GROSS],">"&0,Sold[BUILT],B10,Sold[GOV OCCP],">="&0.5)+COUNTIFS(Ownership[GROSS],">"&0,Ownership[BUILT],B10,Ownership[OCCP],">="&50) | E10: =C10/D10 | F10: =SUMIFS(Sold[RBA],Sold[BUILT],B10,Sold[GROSS],">"&0,Sold[GOV OCCP],">="&0.5)+SUMIFS(Ownership[SF LEASED],Ownership[BUILT],B10,Ownership[GROSS],">"&0,Ownership[OCCP],">="&50) | G10: =F10/D10 | H10: =C10/F10 | I10: {=PERCENTILE(IF(Sold[BUILT]=B10,Sold[GROSS/SF]),0.75)} | J10: {=PERCENTILE(IF(Sold[BUILT]=B10,Sold[GROSS/SF]),0.25)} | K10: {=MEDIAN(IF(Sold[BUILT]=B10,Sold[GROSS/SF]))}
B11: 2017 | C11: =SUMIFS(Sold[GROSS],Sold[BUILT],B11,Sold[GOV OCCP],">="&0.5)+SUMIFS(Ownership[GROSS],Ownership[BUILT],B11,Ownership[OCCP],">="&50) | D11: =COUNTIFS(Sold[GROSS],">"&0,Sold[BUILT],B11,Sold[GOV OCCP],">="&0.5)+COUNTIFS(Ownership[GROSS],">"&0,Ownership[BUILT],B11,Ownership[OCCP],">="&50) | E11: =C11/D11 | F11: =SUMIFS(Sold[RBA],Sold[BUILT],B11,Sold[GROSS],">"&0,Sold[GOV OCCP],">="&0.5)+SUMIFS(Ownership[SF LEASED],Ownership[BUILT],B11,Ownership[GROSS],">"&0,Ownership[OCCP],">="&50) | G11: =F11/D11 | H11: =C11/F11 | I11: {=PERCENTILE(IF(Sold[BUILT]=B11,Sold[GROSS/SF]),0.75)} | J11: {=PERCENTILE(IF(Sold[BUILT]=B11,Sold[GROSS/SF]),0.25)} | K11: {=MEDIAN(IF(Sold[BUILT]=B11,Sold[GROSS/SF]))}
B12: 2016 | C12: =SUMIFS(Sold[GROSS],Sold[BUILT],B12,Sold[GOV OCCP],">="&0.5)+SUMIFS(Ownership[GROSS],Ownership[BUILT],B12,Ownership[OCCP],">="&50) | D12: =COUNTIFS(Sold[GROSS],">"&0,Sold[BUILT],B12,Sold[GOV OCCP],">="&0.5)+COUNTIFS(Ownership[GROSS],">"&0,Ownership[BUILT],B12,Ownership[OCCP],">="&50) | E12: =C12/D12 | F12: =SUMIFS(Sold[RBA],Sold[BUILT],B12,Sold[GROSS],">"&0,Sold[GOV OCCP],">="&0.5)+SUMIFS(Ownership[SF LEASED],Ownership[BUILT],B12,Ownership[GROSS],">"&0,Ownership[OCCP],">="&50) | G12: =F12/D12 | H12: =C12/F12 | I12: {=PERCENTILE(IF(Sold[BUILT]=B12,Sold[GROSS/SF]),0.75)} | J12: {=PERCENTILE(IF(Sold[BUILT]=B12,Sold[GROSS/SF]),0.25)} | K12: {=MEDIAN(IF(Sold[BUILT]=B12,Sold[GROSS/SF]))}
B13: 2015 | C13: =SUMIFS(Sold[GROSS],Sold[BUILT],B13,Sold[GOV OCCP],">="&0.5)+SUMIFS(Ownership[GROSS],Ownership[BUILT],B13,Ownership[OCCP],">="&50) | D13: =COUNTIFS(Sold[GROSS],">"&0,Sold[BUILT],B13,Sold[GOV OCCP],">="&0.5)+COUNTIFS(Ownership[GROSS],">"&0,Ownership[BUILT],B13,Ownership[OCCP],">="&50) | E13: =C13/D13 | F13: =SUMIFS(Sold[RBA],Sold[BUILT],B13,Sold[GROSS],">"&0,Sold[GOV OCCP],">="&0.5)+SUMIFS(Ownership[SF LEASED],Ownership[BUILT],B13,Ownership[GROSS],">"&0,Ownership[OCCP],">="&50) | G13: =F13/D13 | H13: =C13/F13 | I13: {=PERCENTILE(IF(Sold[BUILT]=B13,Sold[GROSS/SF]),0.75)} | J13: {=PERCENTILE(IF(Sold[BUILT]=B13,Sold[GROSS/SF]),0.25)} | K13: {=MEDIAN(IF(Sold[BUILT]=B13,Sold[GROSS/SF]))}
B14: 2014 | C14: =SUMIFS(Sold[GROSS],Sold[BUILT],B14,Sold[GOV OCCP],">="&0.5)+SUMIFS(Ownership[GROSS],Ownership[BUILT],B14,Ownership[OCCP],">="&50) | D14: =COUNTIFS(Sold[GROSS],">"&0,Sold[BUILT],B14,Sold[GOV OCCP],">="&0.5)+COUNTIFS(Ownership[GROSS],">"&0,Ownership[BUILT],B14,Ownership[OCCP],">="&50) | E14: =C14/D14 | F14: =SUMIFS(Sold[RBA],Sold[BUILT],B14,Sold[GROSS],">"&0,Sold[GOV OCCP],">="&0.5)+SUMIFS(Ownership[SF LEASED],Ownership[BUILT],B14,Ownership[GROSS],">"&0,Ownership[OCCP],">="&50) | G14: =F14/D14 | H14: =C14/F14 | I14: {=PERCENTILE(IF(Sold[BUILT]=B14,Sold[GROSS/SF]),0.75)} | J14: {=PERCENTILE(IF(Sold[BUILT]=B14,Sold[GROSS/SF]),0.25)} | K14: {=MEDIAN(IF(Sold[BUILT]=B14,Sold[GROSS/SF]))}
B15: 2013 | C15: =SUMIFS(Sold[GROSS],Sold[BUILT],B15,Sold[GOV OCCP],">="&0.5)+SUMIFS(Ownership[GROSS],Ownership[BUILT],B15,Ownership[OCCP],">="&50) | D15: =COUNTIFS(Sold[GROSS],">"&0,Sold[BUILT],B15,Sold[GOV OCCP],">="&0.5)+COUNTIFS(Ownership[GROSS],">"&0,Ownership[BUILT],B15,Ownership[OCCP],">="&50) | E15: =C15/D15 | F15: =SUMIFS(Sold[RBA],Sold[BUILT],B15,Sold[GROSS],">"&0,Sold[GOV OCCP],">="&0.5)+SUMIFS(Ownership[SF LEASED],Ownership[BUILT],B15,Ownership[GROSS],">"&0,Ownership[OCCP],">="&50) | G15: =F15/D15 | H15: =C15/F15 | I15: {=PERCENTILE(IF(Sold[BUILT]=B15,Sold[GROSS/SF]),0.75)} | J15: {=PERCENTILE(IF(Sold[BUILT]=B15,Sold[GROSS/SF]),0.25)} | K15: {=MEDIAN(IF(Sold[BUILT]=B15,Sold[GROSS/SF]))}
B16: 2012 | C16: =SUMIFS(Sold[GROSS],Sold[BUILT],B16,Sold[GOV OCCP],">="&0.5)+SUMIFS(Ownership[GROSS],Ownership[BUILT],B16,Ownership[OCCP],">="&50) | D16: =COUNTIFS(Sold[GROSS],">"&0,Sold[BUILT],B16,Sold[GOV OCCP],">="&0.5)+COUNTIFS(Ownership[GROSS],">"&0,Ownership[BUILT],B16,Ownership[OCCP],">="&50) | E16: =C16/D16 | F16: =SUMIFS(Sold[RBA],Sold[BUILT],B16,Sold[GROSS],">"&0,Sold[GOV OCCP],">="&0.5)+SUMIFS(Ownership[SF LEASED],Ownership[BUILT],B16,Ownership[GROSS],">"&0,Ownership[OCCP],">="&50) | G16: =F16/D16 | H16: =C16/F16 | I16: {=PERCENTILE(IF(Sold[BUILT]=B16,Sold[GROSS/SF]),0.75)} | J16: {=PERCENTILE(IF(Sold[BUILT]=B16,Sold[GROSS/SF]),0.25)} | K16: {=MEDIAN(IF(Sold[BUILT]=B16,Sold[GROSS/SF]))}
... B36: 1992 | C36: =SUMIFS(Sold[GROSS],Sold[BUILT],B36,Sold[GOV OCCP],">="&0.5)+SUMIFS(Ownership[GROSS],Ownership[BUILT],B36,Ownership[OCCP],">="&50) | D36: =COUNTIFS(Sold[GROSS],">"&0,Sold[BUILT],B36,Sold[GOV OCCP],">="&0.5)+COUNTIFS(Ownership[GROSS],">"&0,Ownership[BUILT],B36,Ownership[OCCP],">="&50) | E36: =C36/D36 | F36: =SUMIFS(Sold[RBA],Sold[BUILT],B36,Sold[GROSS],">"&0,Sold[GOV OCCP],">="&0.5)+SUMIFS(Ownership[SF LEASED],Ownership[BUILT],B36,Ownership[GROSS],">"&0,Ownership[OCCP],">="&50) | G36: =F36/D36 | H36: =C36/F36 | I36: {=PERCENTILE(IF(Sold[BUILT]=B36,Sold[GROSS/SF]),0.75)} | J36: {=PERCENTILE(IF(Sold[BUILT]=B36,Sold[GROSS/SF]),0.25)} | K36: {=MEDIAN(IF(Sold[BUILT]=B36,Sold[GROSS/SF]))}
B38: State | C38: Sum of Rent | D38: Count of Rent | E38: Average Rents | F38: Sum of RBA | G38: Average RBA | H38: Average RPSF | I38: Upper Quartile Rent | J38: Lower Quartile Rent | K38: Median Rent PSF
B39: AL | C39: =SUMIFS(Sold[GROSS],Sold[STATE],B39,Sold[GOV OCCP],">="&0.5)+SUMIFS(Ownership[GROSS],Ownership[STATE],B39,Ownership[OCCP],">="&50) | D39: =COUNTIFS(Sold[GROSS],">"&0,Sold[STATE],B39,Sold[GOV OCCP],">="&0.5)+COUNTIFS(Ownership[GROSS],">"&0,Ownership[STATE],B39,Ownership[OCCP],">="&50) | E39: =C39/D39 | F39: =SUMIFS(Sold[RBA],Sold[STATE],B39,Sold[GROSS],">"&0,Sold[GOV OCCP],">="&0.5)+SUMIFS(Ownership[SF LEASED],Ownership[STATE],B39,Ownership[GROSS],">"&0,Ownership[OCCP],">="&50) | G39: =F39/D39 | H39: =C39/F39 | I39: {=PERCENTILE(IF(Ownership[STATE]=B39,Ownership[GROSS/SF]),0.75)} | J39: {=PERCENTILE(IF(Ownership[STATE]=B39,Ownership[GROSS/SF]),0.25)} | K39: {=MEDIAN(IF(Ownership[STATE]=B39,Ownership[GROSS/SF]))}
B40: AK | C40: =SUMIFS(Sold[GROSS],Sold[STATE],B40,Sold[GOV OCCP],">="&0.5)+SUMIFS(Ownership[GROSS],Ownership[STATE],B40,Ownership[OCCP],">="&50) | D40: =COUNTIFS(Sold[GROSS],">"&0,Sold[STATE],B40,Sold[GOV OCCP],">="&0.5)+COUNTIFS(Ownership[GROSS],">"&0,Ownership[STATE],B40,Ownership[OCCP],">="&50) | E40: =C40/D40 | F40: =SUMIFS(Sold[RBA],Sold[STATE],B40,Sold[GROSS],">"&0,Sold[GOV OCCP],">="&0.5)+SUMIFS(Ownership[SF LEASED],Ownership[STATE],B40,Ownership[GROSS],">"&0,Ownership[OCCP],">="&50) | G40: =F40/D40 | H40: =C40/F40 | I40: {=PERCENTILE(IF(Ownership[STATE]=B40,Ownership[GROSS/SF]),0.75)} | J40: {=PERCENTILE(IF(Ownership[STATE]=B40,Ownership[GROSS/SF]),0.25)} | K40: {=MEDIAN(IF(Ownership[STATE]=B40,Ownership[GROSS/SF]))}
B41: AZ | C41: =SUMIFS(Sold[GROSS],Sold[STATE],B41,Sold[GOV OCCP],">="&0.5)+SUMIFS(Ownership[GROSS],Ownership[STATE],B41,Ownership[OCCP],">="&50) | D41: =COUNTIFS(Sold[GROSS],">"&0,Sold[STATE],B41,Sold[GOV OCCP],">="&0.5)+COUNTIFS(Ownership[GROSS],">"&0,Ownership[STATE],B41,Ownership[OCCP],">="&50) | E41: =C41/D41 | F41: =SUMIFS(Sold[RBA],Sold[STATE],B41,Sold[GROSS],">"&0,Sold[GOV OCCP],">="&0.5)+SUMIFS(Ownership[SF LEASED],Ownership[STATE],B41,Ownership[GROSS],">"&0,Ownership[OCCP],">="&50) | G41: =F41/D41 | H41: =C41/F41 | I41: {=PERCENTILE(IF(Ownership[STATE]=B41,Ownership[GROSS/SF]),0.75)} | J41: {=PERCENTILE(IF(Ownership[STATE]=B41,Ownership[GROSS/SF]),0.25)} | K41: {=MEDIAN(IF(Ownership[STATE]=B41,Ownership[GROSS/SF]))}
B42: AR | C42: =SUMIFS(Sold[GROSS],Sold[STATE],B42,Sold[GOV OCCP],">="&0.5)+SUMIFS(Ownership[GROSS],Ownership[STATE],B42,Ownership[OCCP],">="&50) | D42: =COUNTIFS(Sold[GROSS],">"&0,Sold[STATE],B42,Sold[GOV OCCP],">="&0.5)+COUNTIFS(Ownership[GROSS],">"&0,Ownership[STATE],B42,Ownership[OCCP],">="&50) | E42: =C42/D42 | F42: =SUMIFS(Sold[RBA],Sold[STATE],B42,Sold[GROSS],">"&0,Sold[GOV OCCP],">="&0.5)+SUMIFS(Ownership[SF LEASED],Ownership[STATE],B42,Ownership[GROSS],">"&0,Ownership[OCCP],">="&50) | G42: =F42/D42 | H42: =C42/F42 | I42: {=PERCENTILE(IF(Ownership[STATE]=B42,Ownership[GROSS/SF]),0.75)} | J42: {=PERCENTILE(IF(Ownership[STATE]=B42,Ownership[GROSS/SF]),0.25)} | K42: {=MEDIAN(IF(Ownership[STATE]=B42,Ownership[GROSS/SF]))} | M42: 18 - Rent Heat Map
B43: CA | C43: =SUMIFS(Sold[GROSS],Sold[STATE],B43,Sold[GOV OCCP],">="&0.5)+SUMIFS(Ownership[GROSS],Ownership[STATE],B43,Ownership[OCCP],">="&50) | D43: =COUNTIFS(Sold[GROSS],">"&0,Sold[STATE],B43,Sold[GOV OCCP],">="&0.5)+COUNTIFS(Ownership[GROSS],">"&0,Ownership[STATE],B43,Ownership[OCCP],">="&50) | E43: =C43/D43 | F43: =SUMIFS(Sold[RBA],Sold[STATE],B43,Sold[GROSS],">"&0,Sold[GOV OCCP],">="&0.5)+SUMIFS(Ownership[SF LEASED],Ownership[STATE],B43,Ownership[GROSS],">"&0,Ownership[OCCP],">="&50) | G43: =F43/D43 | H43: =C43/F43 | I43: {=PERCENTILE(IF(Ownership[STATE]=B43,Ownership[GROSS/SF]),0.75)} | J43: {=PERCENTILE(IF(Ownership[STATE]=B43,Ownership[GROSS/SF]),0.25)} | K43: {=MEDIAN(IF(Ownership[STATE]=B43,Ownership[GROSS/SF]))}
B44: CO | C44: =SUMIFS(Sold[GROSS],Sold[STATE],B44,Sold[GOV OCCP],">="&0.5)+SUMIFS(Ownership[GROSS],Ownership[STATE],B44,Ownership[OCCP],">="&50) | D44: =COUNTIFS(Sold[GROSS],">"&0,Sold[STATE],B44,Sold[GOV OCCP],">="&0.5)+COUNTIFS(Ownership[GROSS],">"&0,Ownership[STATE],B44,Ownership[OCCP],">="&50) | E44: =C44/D44 | F44: =SUMIFS(Sold[RBA],Sold[STATE],B44,Sold[GROSS],">"&0,Sold[GOV OCCP],">="&0.5)+SUMIFS(Ownership[SF LEASED],Ownership[STATE],B44,Ownership[GROSS],">"&0,Ownership[OCCP],">="&50) | G44: =F44/D44 | H44: =C44/F44 | I44: {=PERCENTILE(IF(Ownership[STATE]=B44,Ownership[GROSS/SF]),0.75)} | J44: {=PERCENTILE(IF(Ownership[STATE]=B44,Ownership[GROSS/SF]),0.25)} | K44: {=MEDIAN(IF(Ownership[STATE]=B44,Ownership[GROSS/SF]))}
B45: CT | C45: =SUMIFS(Sold[GROSS],Sold[STATE],B45,Sold[GOV OCCP],">="&0.5)+SUMIFS(Ownership[GROSS],Ownership[STATE],B45,Ownership[OCCP],">="&50) | D45: =COUNTIFS(Sold[GROSS],">"&0,Sold[STATE],B45,Sold[GOV OCCP],">="&0.5)+COUNTIFS(Ownership[GROSS],">"&0,Ownership[STATE],B45,Ownership[OCCP],">="&50) | E45: =C45/D45 | F45: =SUMIFS(Sold[RBA],Sold[STATE],B45,Sold[GROSS],">"&0,Sold[GOV OCCP],">="&0.5)+SUMIFS(Ownership[SF LEASED],Ownership[STATE],B45,Ownership[GROSS],">"&0,Ownership[OCCP],">="&50) | G45: =F45/D45 | H45: =C45/F45 | I45: {=PERCENTILE(IF(Ownership[STATE]=B45,Ownership[GROSS/SF]),0.75)} | J45: {=PERCENTILE(IF(Ownership[STATE]=B45,Ownership[GROSS/SF]),0.25)} | K45: {=MEDIAN(IF(Ownership[STATE]=B45,Ownership[GROSS/SF]))}
B46: DE | C46: =SUMIFS(Sold[GROSS],Sold[STATE],B46,Sold[GOV OCCP],">="&0.5)+SUMIFS(Ownership[GROSS],Ownership[STATE],B46,Ownership[OCCP],">="&50) | D46: =COUNTIFS(Sold[GROSS],">"&0,Sold[STATE],B46,Sold[GOV OCCP],">="&0.5)+COUNTIFS(Ownership[GROSS],">"&0,Ownership[STATE],B46,Ownership[OCCP],">="&50) | E46: =C46/D46 | F46: =SUMIFS(Sold[RBA],Sold[STATE],B46,Sold[GROSS],">"&0,Sold[GOV OCCP],">="&0.5)+SUMIFS(Ownership[SF LEASED],Ownership[STATE],B46,Ownership[GROSS],">"&0,Ownership[OCCP],">="&50) | G46: =F46/D46 | H46: =C46/F46 | I46: {=PERCENTILE(IF(Ownership[STATE]=B46,Ownership[GROSS/SF]),0.75)} | J46: {=PERCENTILE(IF(Ownership[STATE]=B46,Ownership[GROSS/SF]),0.25)} | K46: {=MEDIAN(IF(Ownership[STATE]=B46,Ownership[GROSS/SF]))}
B47: DC | C47: =SUMIFS(Sold[GROSS],Sold[STATE],B47,Sold[GOV OCCP],">="&0.5)+SUMIFS(Ownership[GROSS],Ownership[STATE],B47,Ownership[OCCP],">="&50) | D47: =COUNTIFS(Sold[GROSS],">"&0,Sold[STATE],B47,Sold[GOV OCCP],">="&0.5)+COUNTIFS(Ownership[GROSS],">"&0,Ownership[STATE],B47,Ownership[OCCP],">="&50) | E47: =C47/D47 | F47: =SUMIFS(Sold[RBA],Sold[STATE],B47,Sold[GROSS],">"&0,Sold[GOV OCCP],">="&0.5)+SUMIFS(Ownership[SF LEASED],Ownership[STATE],B47,Ownership[GROSS],">"&0,Ownership[OCCP],">="&50) | G47: =F47/D47 | H47: =C47/F47 | I47: {=PERCENTILE(IF(Ownership[STATE]=B47,Ownership[GROSS/SF]),0.75)} | J47: {=PERCENTILE(IF(Ownership[STATE]=B47,Ownership[GROSS/SF]),0.25)} | K47: {=MEDIAN(IF(Ownership[STATE]=B47,Ownership[GROSS/SF]))}
B48: FL | C48: =SUMIFS(Sold[GROSS],Sold[STATE],B48,Sold[GOV OCCP],">="&0.5)+SUMIFS(Ownership[GROSS],Ownership[STATE],B48,Ownership[OCCP],">="&50) | D48: =COUNTIFS(Sold[GROSS],">"&0,Sold[STATE],B48,Sold[GOV OCCP],">="&0.5)+COUNTIFS(Ownership[GROSS],">"&0,Ownership[STATE],B48,Ownership[OCCP],">="&50) | E48: =C48/D48 | F48: =SUMIFS(Sold[RBA],Sold[STATE],B48,Sold[GROSS],">"&0,Sold[GOV OCCP],">="&0.5)+SUMIFS(Ownership[SF LEASED],Ownership[STATE],B48,Ownership[GROSS],">"&0,Ownership[OCCP],">="&50) | G48: =F48/D48 | H48: =C48/F48 | I48: {=PERCENTILE(IF(Ownership[STATE]=B48,Ownership[GROSS/SF]),0.75)} | J48: {=PERCENTILE(IF(Ownership[STATE]=B48,Ownership[GROSS/SF]),0.25)} | K48: {=MEDIAN(IF(Ownership[STATE]=B48,Ownership[GROSS/SF]))}
B49: GA | C49: =SUMIFS(Sold[GROSS],Sold[STATE],B49,Sold[GOV OCCP],">="&0.5)+SUMIFS(Ownership[GROSS],Ownership[STATE],B49,Ownership[OCCP],">="&50) | D49: =COUNTIFS(Sold[GROSS],">"&0,Sold[STATE],B49,Sold[GOV OCCP],">="&0.5)+COUNTIFS(Ownership[GROSS],">"&0,Ownership[STATE],B49,Ownership[OCCP],">="&50) | E49: =C49/D49 | F49: =SUMIFS(Sold[RBA],Sold[STATE],B49,Sold[GROSS],">"&0,Sold[GOV OCCP],">="&0.5)+SUMIFS(Ownership[SF LEASED],Ownership[STATE],B49,Ownership[GROSS],">"&0,Ownership[OCCP],">="&50) | G49: =F49/D49 | H49: =C49/F49 | I49: {=PERCENTILE(IF(Ownership[STATE]=B49,Ownership[GROSS/SF]),0.75)} | J49: {=PERCENTILE(IF(Ownership[STATE]=B49,Ownership[GROSS/SF]),0.25)} | K49: {=MEDIAN(IF(Ownership[STATE]=B49,Ownership[GROSS/SF]))}
B50: HI | C50: =SUMIFS(Sold[GROSS],Sold[STATE],B50,Sold[GOV OCCP],">="&0.5)+SUMIFS(Ownership[GROSS],Ownership[STATE],B50,Ownership[OCCP],">="&50) | D50: =COUNTIFS(Sold[GROSS],">"&0,Sold[STATE],B50,Sold[GOV OCCP],">="&0.5)+COUNTIFS(Ownership[GROSS],">"&0,Ownership[STATE],B50,Ownership[OCCP],">="&50) | E50: =C50/D50 | F50: =SUMIFS(Sold[RBA],Sold[STATE],B50,Sold[GROSS],">"&0,Sold[GOV OCCP],">="&0.5)+SUMIFS(Ownership[SF LEASED],Ownership[STATE],B50,Ownership[GROSS],">"&0,Ownership[OCCP],">="&50) | G50: =F50/D50 | H50: =C50/F50 | I50: {=PERCENTILE(IF(Ownership[STATE]=B50,Ownership[GROSS/SF]),0.75)} | J50: {=PERCENTILE(IF(Ownership[STATE]=B50,Ownership[GROSS/SF]),0.25)} | K50: {=MEDIAN(IF(Ownership[STATE]=B50,Ownership[GROSS/SF]))}
B51: ID | C51: =SUMIFS(Sold[GROSS],Sold[STATE],B51,Sold[GOV OCCP],">="&0.5)+SUMIFS(Ownership[GROSS],Ownership[STATE],B51,Ownership[OCCP],">="&50) | D51: =COUNTIFS(Sold[GROSS],">"&0,Sold[STATE],B51,Sold[GOV OCCP],">="&0.5)+COUNTIFS(Ownership[GROSS],">"&0,Ownership[STATE],B51,Ownership[OCCP],">="&50) | E51: =C51/D51 | F51: =SUMIFS(Sold[RBA],Sold[STATE],B51,Sold[GROSS],">"&0,Sold[GOV OCCP],">="&0.5)+SUMIFS(Ownership[SF LEASED],Ownership[STATE],B51,Ownership[GROSS],">"&0,Ownership[OCCP],">="&50) | G51: =F51/D51 | H51: =C51/F51 | I51: {=PERCENTILE(IF(Ownership[STATE]=B51,Ownership[GROSS/SF]),0.75)} | J51: {=PERCENTILE(IF(Ownership[STATE]=B51,Ownership[GROSS/SF]),0.25)} | K51: {=MEDIAN(IF(Ownership[STATE]=B51,Ownership[GROSS/SF]))}
B52: IL | C52: =SUMIFS(Sold[GROSS],Sold[STATE],B52,Sold[GOV OCCP],">="&0.5)+SUMIFS(Ownership[GROSS],Ownership[STATE],B52,Ownership[OCCP],">="&50) | D52: =COUNTIFS(Sold[GROSS],">"&0,Sold[STATE],B52,Sold[GOV OCCP],">="&0.5)+COUNTIFS(Ownership[GROSS],">"&0,Ownership[STATE],B52,Ownership[OCCP],">="&50) | E52: =C52/D52 | F52: =SUMIFS(Sold[RBA],Sold[STATE],B52,Sold[GROSS],">"&0,Sold[GOV OCCP],">="&0.5)+SUMIFS(Ownership[SF LEASED],Ownership[STATE],B52,Ownership[GROSS],">"&0,Ownership[OCCP],">="&50) | G52: =F52/D52 | H52: =C52/F52 | I52: {=PERCENTILE(IF(Ownership[STATE]=B52,Ownership[GROSS/SF]),0.75)} | J52: {=PERCENTILE(IF(Ownership[STATE]=B52,Ownership[GROSS/SF]),0.25)} | K52: {=MEDIAN(IF(Ownership[STATE]=B52,Ownership[GROSS/SF]))}
B53: IN | C53: =SUMIFS(Sold[GROSS],Sold[STATE],B53,Sold[GOV OCCP],">="&0.5)+SUMIFS(Ownership[GROSS],Ownership[STATE],B53,Ownership[OCCP],">="&50) | D53: =COUNTIFS(Sold[GROSS],">"&0,Sold[STATE],B53,Sold[GOV OCCP],">="&0.5)+COUNTIFS(Ownership[GROSS],">"&0,Ownership[STATE],B53,Ownership[OCCP],">="&50) | E53: =C53/D53 | F53: =SUMIFS(Sold[RBA],Sold[STATE],B53,Sold[GROSS],">"&0,Sold[GOV OCCP],">="&0.5)+SUMIFS(Ownership[SF LEASED],Ownership[STATE],B53,Ownership[GROSS],">"&0,Ownership[OCCP],">="&50) | G53: =F53/D53 | H53: =C53/F53 | I53: {=PERCENTILE(IF(Ownership[STATE]=B53,Ownership[GROSS/SF]),0.75)} | J53: {=PERCENTILE(IF(Ownership[STATE]=B53,Ownership[GROSS/SF]),0.25)} | K53: {=MEDIAN(IF(Ownership[STATE]=B53,Ownership[GROSS/SF]))}
B54: IA | C54: =SUMIFS(Sold[GROSS],Sold[STATE],B54,Sold[GOV OCCP],">="&0.5)+SUMIFS(Ownership[GROSS],Ownership[STATE],B54,Ownership[OCCP],">="&50) | D54: =COUNTIFS(Sold[GROSS],">"&0,Sold[STATE],B54,Sold[GOV OCCP],">="&0.5)+COUNTIFS(Ownership[GROSS],">"&0,Ownership[STATE],B54,Ownership[OCCP],">="&50) | E54: =C54/D54 | F54: =SUMIFS(Sold[RBA],Sold[STATE],B54,Sold[GROSS],">"&0,Sold[GOV OCCP],">="&0.5)+SUMIFS(Ownership[SF LEASED],Ownership[STATE],B54,Ownership[GROSS],">"&0,Ownership[OCCP],">="&50) | G54: =F54/D54 | H54: =C54/F54 | I54: {=PERCENTILE(IF(Ownership[STATE]=B54,Ownership[GROSS/SF]),0.75)} | J54: {=PERCENTILE(IF(Ownership[STATE]=B54,Ownership[GROSS/SF]),0.25)} | K54: {=MEDIAN(IF(Ownership[STATE]=B54,Ownership[GROSS/SF]))}
... B89: WY | C89: =SUMIFS(Sold[GROSS],Sold[STATE],B89,Sold[GOV OCCP],">="&0.5)+SUMIFS(Ownership[GROSS],Ownership[STATE],B89,Ownership[OCCP],">="&50) | D89: =COUNTIFS(Sold[GROSS],">"&0,Sold[STATE],B89,Sold[GOV OCCP],">="&0.5)+COUNTIFS(Ownership[GROSS],">"&0,Ownership[STATE],B89,Ownership[OCCP],">="&50) | E89: =C89/D89 | F89: =SUMIFS(Sold[RBA],Sold[STATE],B89,Sold[GROSS],">"&0,Sold[GOV OCCP],">="&0.5)+SUMIFS(Ownership[SF LEASED],Ownership[STATE],B89,Ownership[GROSS],">"&0,Ownership[OCCP],">="&50) | G89: =F89/D89 | H89: =C89/F89 | I89: {=PERCENTILE(IF(Ownership[STATE]=B89,Ownership[GROSS/SF]),0.75)} | J89: {=PERCENTILE(IF(Ownership[STATE]=B89,Ownership[GROSS/SF]),0.25)} | K89: {=MEDIAN(IF(Ownership[STATE]=B89,Ownership[GROSS/SF]))}
A91: 45657 | B91: Year Commenced | C91: Sum of Rent | D91: Count of Rent | E91: Average Rents | F91: Sum of RBA | G91: Average RBA | H91: Average RPSF | I91: Upper Quartile Rent | J91: Lower Quartile Rent | K91: Median Rent PSF | M91: 16 - Case for Renewal
A92: 45291 | B92: 2023 | C92: =SUMIFS(Ownership[GROSS],Ownership[COM],">"&A93,Ownership[COM],"<="&A92,Ownership[OCCP],">="&50) | D92: =COUNTIFS(Ownership[GROSS],">"&0,Ownership[COM],">"&A93,Ownership[COM],"<="&A92,Ownership[OCCP],">="&50) | E92: =C92/D92 | F92: =SUMIFS(Ownership[SF LEASED],Ownership[COM],">"&A93,Ownership[COM],"<="&A92,Ownership[GROSS],">"&0,Ownership[OCCP],">="&50) | G92: =F92/D92 | H92: =C92/F92
A93: =EDATE(A92,-12) | B93: 2022 | C93: =SUMIFS(Ownership[GROSS],Ownership[COM],">"&A94,Ownership[COM],"<="&A93,Ownership[OCCP],">="&50) | D93: =COUNTIFS(Ownership[GROSS],">"&0,Ownership[COM],">"&A94,Ownership[COM],"<="&A93,Ownership[OCCP],">="&50) | E93: =C93/D93 | F93: =SUMIFS(Ownership[SF LEASED],Ownership[COM],">"&A94,Ownership[COM],"<="&A93,Ownership[GROSS],">"&0,Ownership[OCCP],">="&50) | G93: =F93/D93 | H93: =C93/F93
A94: =EDATE(A93,-12) | B94: 2021 | C94: =SUMIFS(Ownership[GROSS],Ownership[COM],">"&A95,Ownership[COM],"<="&A94,Ownership[OCCP],">="&50) | D94: =COUNTIFS(Ownership[GROSS],">"&0,Ownership[COM],">"&A95,Ownership[COM],"<="&A94,Ownership[OCCP],">="&50) | E94: =C94/D94 | F94: =SUMIFS(Ownership[SF LEASED],Ownership[COM],">"&A95,Ownership[COM],"<="&A94,Ownership[GROSS],">"&0,Ownership[OCCP],">="&50) | G94: =F94/D94 | H94: =C94/F94
A95: =EDATE(A94,-12) | B95: 2020 | C95: =SUMIFS(Ownership[GROSS],Ownership[COM],">"&A96,Ownership[COM],"<="&A95,Ownership[OCCP],">="&50) | D95: =COUNTIFS(Ownership[GROSS],">"&0,Ownership[COM],">"&A96,Ownership[COM],"<="&A95,Ownership[OCCP],">="&50) | E95: =C95/D95 | F95: =SUMIFS(Ownership[SF LEASED],Ownership[COM],">"&A96,Ownership[COM],"<="&A95,Ownership[GROSS],">"&0,Ownership[OCCP],">="&50) | G95: =F95/D95 | H95: =C95/F95
A96: =EDATE(A95,-12) | B96: 2019 | C96: =SUMIFS(Ownership[GROSS],Ownership[COM],">"&A97,Ownership[COM],"<="&A96,Ownership[OCCP],">="&50) | D96: =COUNTIFS(Ownership[GROSS],">"&0,Ownership[COM],">"&A97,Ownership[COM],"<="&A96,Ownership[OCCP],">="&50) | E96: =C96/D96 | F96: =SUMIFS(Ownership[SF LEASED],Ownership[COM],">"&A97,Ownership[COM],"<="&A96,Ownership[GROSS],">"&0,Ownership[OCCP],">="&50) | G96: =F96/D96 | H96: =C96/F96
A97: =EDATE(A96,-12) | B97: 2018 | C97: =SUMIFS(Ownership[GROSS],Ownership[COM],">"&A98,Ownership[COM],"<="&A97,Ownership[OCCP],">="&50) | D97: =COUNTIFS(Ownership[GROSS],">"&0,Ownership[COM],">"&A98,Ownership[COM],"<="&A97,Ownership[OCCP],">="&50) | E97: =C97/D97 | F97: =SUMIFS(Ownership[SF LEASED],Ownership[COM],">"&A98,Ownership[COM],"<="&A97,Ownership[GROSS],">"&0,Ownership[OCCP],">="&50) | G97: =F97/D97 | H97: =C97/F97
A98: =EDATE(A97,-12) | B98: 2017 | C98: =SUMIFS(Ownership[GROSS],Ownership[COM],">"&A99,Ownership[COM],"<="&A98,Ownership[OCCP],">="&50) | D98: =COUNTIFS(Ownership[GROSS],">"&0,Ownership[COM],">"&A99,Ownership[COM],"<="&A98,Ownership[OCCP],">="&50) | E98: =C98/D98 | F98: =SUMIFS(Ownership[SF LEASED],Ownership[COM],">"&A99,Ownership[COM],"<="&A98,Ownership[GROSS],">"&0,Ownership[OCCP],">="&50) | G98: =F98/D98 | H98: =C98/F98
A99: =EDATE(A98,-12) | B99: 2016 | C99: =SUMIFS(Ownership[GROSS],Ownership[COM],">"&A100,Ownership[COM],"<="&A99,Ownership[OCCP],">="&50) | D99: =COUNTIFS(Ownership[GROSS],">"&0,Ownership[COM],">"&A100,Ownership[COM],"<="&A99,Ownership[OCCP],">="&50) | E99: =C99/D99 | F99: =SUMIFS(Ownership[SF LEASED],Ownership[COM],">"&A100,Ownership[COM],"<="&A99,Ownership[GROSS],">"&0,Ownership[OCCP],">="&50) | G99: =F99/D99 | H99: =C99/F99
A100: =EDATE(A99,-12) | B100: 2015 | C100: =SUMIFS(Ownership[GROSS],Ownership[COM],">"&A101,Ownership[COM],"<="&A100,Ownership[OCCP],">="&50) | D100: =COUNTIFS(Ownership[GROSS],">"&0,Ownership[COM],">"&A101,Ownership[COM],"<="&A100,Ownership[OCCP],">="&50) | E100: =C100/D100 | F100: =SUMIFS(Ownership[SF LEASED],Ownership[COM],">"&A101,Ownership[COM],"<="&A100,Ownership[GROSS],">"&0,Ownership[OCCP],">="&50) | G100: =F100/D100 | H100: =C100/F100
A101: =EDATE(A100,-12) | B101: 2014 | C101: =SUMIFS(Ownership[GROSS],Ownership[COM],">"&A102,Ownership[COM],"<="&A101,Ownership[OCCP],">="&50) | D101: =COUNTIFS(Ownership[GROSS],">"&0,Ownership[COM],">"&A102,Ownership[COM],"<="&A101,Ownership[OCCP],">="&50) | E101: =C101/D101 | F101: =SUMIFS(Ownership[SF LEASED],Ownership[COM],">"&A102,Ownership[COM],"<="&A101,Ownership[GROSS],">"&0,Ownership[OCCP],">="&50) | G101: =F101/D101 | H101: =C101/F101
A102: =EDATE(A101,-12) | B102: 2013 | C102: =SUMIFS(Ownership[GROSS],Ownership[COM],">"&A103,Ownership[COM],"<="&A102,Ownership[OCCP],">="&50) | D102: =COUNTIFS(Ownership[GROSS],">"&0,Ownership[COM],">"&A103,Ownership[COM],"<="&A102,Ownership[OCCP],">="&50) | E102: =C102/D102 | F102: =SUMIFS(Ownership[SF LEASED],Ownership[COM],">"&A103,Ownership[COM],"<="&A102,Ownership[GROSS],">"&0,Ownership[OCCP],">="&50) | G102: =F102/D102 | H102: =C102/F102
A103: =EDATE(A102,-12) | B103: 2012 | C103: =SUMIFS(Ownership[GROSS],Ownership[COM],">"&A104,Ownership[COM],"<="&A103,Ownership[OCCP],">="&50) | D103: =COUNTIFS(Ownership[GROSS],">"&0,Ownership[COM],">"&A104,Ownership[COM],"<="&A103,Ownership[OCCP],">="&50) | E103: =C103/D103 | F103: =SUMIFS(Ownership[SF LEASED],Ownership[COM],">"&A104,Ownership[COM],"<="&A103,Ownership[GROSS],">"&0,Ownership[OCCP],">="&50) | G103: =F103/D103 | H103: =C103/F103
A104: =EDATE(A103,-12) | B104: 2011 | C104: =SUMIFS(Ownership[GROSS],Ownership[COM],">"&A105,Ownership[COM],"<="&A104,Ownership[OCCP],">="&50) | D104: =COUNTIFS(Ownership[GROSS],">"&0,Ownership[COM],">"&A105,Ownership[COM],"<="&A104,Ownership[OCCP],">="&50) | E104: =C104/D104 | F104: =SUMIFS(Ownership[SF LEASED],Ownership[COM],">"&A105,Ownership[COM],"<="&A104,Ownership[GROSS],">"&0,Ownership[OCCP],">="&50) | G104: =F104/D104 | H104: =C104/F104
... A125: =EDATE(A124,-12) | B125: 1990 | C125: =SUMIFS(Ownership[GROSS],Ownership[COM],">"&A126,Ownership[COM],"<="&A125,Ownership[OCCP],">="&50) | D125: =COUNTIFS(Ownership[GROSS],">"&0,Ownership[COM],">"&A126,Ownership[COM],"<="&A125,Ownership[OCCP],">="&50) | E125: =C125/D125 | F125: =SUMIFS(Ownership[SF LEASED],Ownership[COM],">"&A126,Ownership[COM],"<="&A125,Ownership[GROSS],">"&0,Ownership[OCCP],">="&50) | G125: =F125/D125 | H125: =C125/F125

Sheet Top Buyers

Sheet Top Sellers

Sheet Competition
B1: ALL TIME | I1: ALL TIME
B2: Broker | C2: Volume | D2: Deal Count | E2: Avg. Size | F2: Avg. Cap | G2: Market Share | I2: Firm | J2: Volume | K2: Deal Count | L2: Avg. Size | M2: Avg. Cap | N2: Market Share
B3: Travis Trautvetter | C3: =SUMIFS(Sold[SOLD PRICE],Sold[L. BROKER],"*traut*")+SUMIFS(Sold[SOLD PRICE],Sold[P. BROKER],"*traut*") | D3: =COUNTIFS(Sold[L. BROKER],"*Traut*")+COUNTIFS(Sold[P. BROKER],"*traut*") | E3: =C3/D3 | F3: =AVERAGE((AVERAGEIFS(Sold[SOLD CAP],Sold[L. BROKER],"*Traut*")),(AVERAGEIFS(Sold[SOLD CAP],Sold[P. BROKER],"*traut*"))) | G3: =D3/Sold[[#Totals],[DATE]] | I3: M&M | J3: =SUMIFS(Sold[SOLD PRICE],Sold[L. BROKER],"*M&M*")+SUMIFS(Sold[SOLD PRICE],Sold[P. BROKER],"*M&M*") | K3: =COUNTIFS(Sold[L. BROKER],"*M&M*")+COUNTIFS(Sold[P. BROKER],"*M&M*") | L3: =J3/K3 | M3: =AVERAGEIFS(Sold[SOLD CAP],Sold[L. BROKER],"*M&M*") | N3: =K3/Sold[[#Totals],[DATE]]
B4: Geoff Ficke | C4: =SUMIFS(Sold[SOLD PRICE],Sold[L. BROKER],"*ficke*")+SUMIFS(Sold[SOLD PRICE],Sold[P. BROKER],"*ficke*") | D4: =COUNTIFS(Sold[L. BROKER],"*ficke*")+COUNTIFS(Sold[P. BROKER],"*ficke*") | E4: =C4/D4 | F4: =AVERAGE((AVERAGEIFS(Sold[SOLD CAP],Sold[L. BROKER],"*Ficke*")),(AVERAGEIFS(Sold[SOLD CAP],Sold[P. BROKER],"*Ficke*"))) | G4: =D4/Sold[[#Totals],[DATE]] | I4: C&W | J4: =SUMIFS(Sold[SOLD PRICE],Sold[L. BROKER],"*C&W*")+SUMIFS(Sold[SOLD PRICE],Sold[P. BROKER],"*C&W*") | K4: =COUNTIFS(Sold[L. BROKER],"*C&W*")+COUNTIFS(Sold[P. BROKER],"*C&W*") | L4: =J4/K4 | M4: =AVERAGEIFS(Sold[SOLD CAP],Sold[L. BROKER],"*C&W*") | N4: =K4/Sold[[#Totals],[DATE]]
B5: Jamie Harrison | C5: =SUMIFS(Sold[SOLD PRICE],Sold[L. BROKER],"*Harrison*")+SUMIFS(Sold[SOLD PRICE],Sold[P. BROKER],"*Harrison*") | D5: =COUNTIFS(Sold[L. BROKER],"*Harrison*")+COUNTIFS(Sold[P. BROKER],"*Harrison*") | E5: =C5/D5 | F5: =AVERAGE((AVERAGEIFS(Sold[SOLD CAP],Sold[L. BROKER],"*Harrison*")),(AVERAGEIFS(Sold[SOLD CAP],Sold[P. BROKER],"*Harrison*"))) | G5: =D5/Sold[[#Totals],[DATE]] | I5: CBRE | J5: =SUMIFS(Sold[SOLD PRICE],Sold[L. BROKER],"*CBRE*")+SUMIFS(Sold[SOLD PRICE],Sold[P. BROKER],"*CBRE*") | K5: =COUNTIFS(Sold[L. BROKER],"*CBRE*")+COUNTIFS(Sold[P. BROKER],"*CBRE*") | L5: =J5/K5 | M5: =AVERAGEIFS(Sold[SOLD CAP],Sold[L. BROKER],"*CBRE*") | N5: =K5/Sold[[#Totals],[DATE]]
B6: William Collins | C6: =SUMIFS(Sold[SOLD PRICE],Sold[L. BROKER],"*Collins*")+SUMIFS(Sold[SOLD PRICE],Sold[P. BROKER],"*Collins*") | D6: =COUNTIFS(Sold[L. BROKER],"*Collins*")+COUNTIFS(Sold[P. BROKER],"*Collins*") | E6: =C6/D6 | F6: =AVERAGEIFS(Sold[SOLD CAP],Sold[L. BROKER],"*Collins*") | G6: =D6/Sold[[#Totals],[DATE]] | I6: SJC | J6: =SUMIFS(Sold[SOLD PRICE],Sold[L. BROKER],"*SJC*")+SUMIFS(Sold[SOLD PRICE],Sold[P. BROKER],"*SJC*") | K6: =COUNTIFS(Sold[L. BROKER],"*SJC*")+COUNTIFS(Sold[P. BROKER],"*SJC*") | L6: =J6/K6 | M6: =AVERAGEIFS(Sold[SOLD CAP],Sold[L. BROKER],"*SJC*") | N6: =K6/Sold[[#Totals],[DATE]]
B7: Karen Wells | C7: =SUMIFS(Sold[SOLD PRICE],Sold[L. BROKER],"*wells*")+SUMIFS(Sold[SOLD PRICE],Sold[P. BROKER],"*wells*") | D7: =COUNTIFS(Sold[L. BROKER],"*wells*")+COUNTIFS(Sold[P. BROKER],"*wells*") | E7: =C7/D7 | F7: =AVERAGE((AVERAGEIFS(Sold[SOLD CAP],Sold[L. BROKER],"*Wells*")),(AVERAGEIFS(Sold[SOLD CAP],Sold[P. BROKER],"*Wells*"))) | G7: =D7/Sold[[#Totals],[DATE]] | I7: Colliers | J7: =SUMIFS(Sold[SOLD PRICE],Sold[L. BROKER],"*Colliers*")+SUMIFS(Sold[SOLD PRICE],Sold[P. BROKER],"*Colliers*") | K7: =COUNTIFS(Sold[L. BROKER],"*Colliers*")+COUNTIFS(Sold[P. BROKER],"*Colliers*") | L7: =J7/K7 | M7: =AVERAGEIFS(Sold[SOLD CAP],Sold[L. BROKER],"*Colliers*") | N7: =K7/Sold[[#Totals],[DATE]]
B8: Andy Gallas | C8: =SUMIFS(Sold[SOLD PRICE],Sold[L. BROKER],"*gallas*")+SUMIFS(Sold[SOLD PRICE],Sold[P. BROKER],"*gallas*") | D8: =COUNTIFS(Sold[L. BROKER],"*gallas*")+COUNTIFS(Sold[P. BROKER],"*gallas*") | E8: =C8/D8 | F8: =AVERAGE((AVERAGEIFS(Sold[SOLD CAP],Sold[L. BROKER],"*Gallas*")),(AVERAGEIFS(Sold[SOLD CAP],Sold[P. BROKER],"*Gallas*"))) | G8: =D8/Sold[[#Totals],[DATE]] | I8: JLL | J8: =SUMIFS(Sold[SOLD PRICE],Sold[L. BROKER],"*JLL*")+SUMIFS(Sold[SOLD PRICE],Sold[P. BROKER],"*JLL*") | K8: =COUNTIFS(Sold[L. BROKER],"*JLL*")+COUNTIFS(Sold[P. BROKER],"*JLL*") | L8: =J8/K8 | M8: =AVERAGEIFS(Sold[SOLD CAP],Sold[L. BROKER],"*JLL*") | N8: =K8/Sold[[#Totals],[DATE]]
B9: Bob Cottle | C9: =SUMIFS(Sold[SOLD PRICE],Sold[L. BROKER],"*Cottle*")+SUMIFS(Sold[SOLD PRICE],Sold[P. BROKER],"*Cottle*") | D9: =COUNTIFS(Sold[L. BROKER],"*Cottle*")+COUNTIFS(Sold[P. BROKER],"*Cottle*") | E9: =C9/D9 | F9: =AVERAGEIFS(Sold[SOLD CAP],Sold[L. BROKER],"*Cottle*") | G9: =D9/Sold[[#Totals],[DATE]] | I9: Newmark | J9: =SUMIFS(Sold[SOLD PRICE],Sold[L. BROKER],"*newmark*")+SUMIFS(Sold[SOLD PRICE],Sold[P. BROKER],"*newmark*") | K9: =COUNTIFS(Sold[L. BROKER],"*newmark*")+COUNTIFS(Sold[P. BROKER],"*newmark*") | L9: =J9/K9 | M9: =AVERAGEIFS(Sold[SOLD CAP],Sold[L. BROKER],"*newmark*") | N9: =K9/Sold[[#Totals],[DATE]]
B10: Darrin Kennedy | C10: =SUMIFS(Sold[SOLD PRICE],Sold[L. BROKER],"*Kennedy*")+SUMIFS(Sold[SOLD PRICE],Sold[P. BROKER],"*Kennedy*") | D10: =COUNTIFS(Sold[L. BROKER],"*Kennedy*")+COUNTIFS(Sold[P. BROKER],"*Kennedy*") | E10: =C10/D10 | F10: =AVERAGEIFS(Sold[SOLD CAP],Sold[L. BROKER],"*Kennedy*") | G10: =D10/Sold[[#Totals],[DATE]] | I10: Capital Pacific | J10: =SUMIFS(Sold[SOLD PRICE],Sold[L. BROKER],"*CP;*")+SUMIFS(Sold[SOLD PRICE],Sold[P. BROKER],"*CP;*") | K10: =COUNTIFS(Sold[L. BROKER],"*CP;*")+COUNTIFS(Sold[P. BROKER],"*CP;*") | L10: =J10/K10 | M10: =AVERAGEIFS(Sold[SOLD CAP],Sold[L. BROKER],"*CP;*") | N10: =K10/Sold[[#Totals],[DATE]]
B11: Scott Briggs | C11: =SUMIFS(Sold[SOLD PRICE],Sold[L. BROKER],"*briggs*")+SUMIFS(Sold[SOLD PRICE],Sold[P. BROKER],"*briggs*") | D11: =COUNTIFS(Sold[L. BROKER],"*briggs*")+COUNTIFS(Sold[P. BROKER],"*briggs*") | E11: =C11/D11 | F11: =(AVERAGEIFS(Sold[SOLD CAP],Sold[L. BROKER],"*Briggs*")) | G11: =D11/Sold[[#Totals],[DATE]] | I11: Touchstone | J11: =SUMIFS(Sold[SOLD PRICE],Sold[L. BROKER],"*TCP;*")+SUMIFS(Sold[SOLD PRICE],Sold[P. BROKER],"*TCP;*") | K11: =COUNTIFS(Sold[L. BROKER],"*TCP;*")+COUNTIFS(Sold[P. BROKER],"*TCP;*") | L11: =J11/K11 | M11: =AVERAGEIFS(Sold[SOLD CAP],Sold[L. BROKER],"*TCP*") | N11: =K11/Sold[[#Totals],[DATE]]
B12: Alex Mobin | C12: =SUMIFS(Sold[SOLD PRICE],Sold[L. BROKER],"*Mobin*")+SUMIFS(Sold[SOLD PRICE],Sold[P. BROKER],"*Mobin*") | D12: =COUNTIFS(Sold[L. BROKER],"*Mobin*")+COUNTIFS(Sold[P. BROKER],"*Mobin*") | E12: =C12/D12 | F12: =AVERAGE((AVERAGEIFS(Sold[SOLD CAP],Sold[L. BROKER],"*Mobin*")),(AVERAGEIFS(Sold[SOLD CAP],Sold[P. BROKER],"*Mobin*"))) | G12: =D12/Sold[[#Totals],[DATE]] | I12: Bear Wells | J12: =SUMIFS(Sold[SOLD PRICE],Sold[L. BROKER],"*BW;*")+SUMIFS(Sold[SOLD PRICE],Sold[P. BROKER],"*BW;*") | K12: =COUNTIFS(Sold[L. BROKER],"*BW;*")+COUNTIFS(Sold[P. BROKER],"*BW;*") | L12: =J12/K12 | M12: =AVERAGEIFS(Sold[SOLD CAP],Sold[L. BROKER],"*BW;*") | N12: =K12/Sold[[#Totals],[DATE]]
B13: Justin Fenn | C13: =SUMIFS(Sold[SOLD PRICE],Sold[L. BROKER],"*fenn*")+SUMIFS(Sold[SOLD PRICE],Sold[P. BROKER],"*fenn*") | D13: =COUNTIFS(Sold[L. BROKER],"*fenn*")+COUNTIFS(Sold[P. BROKER],"*fenn*") | E13: =C13/D13 | F13: =AVERAGEIFS(Sold[SOLD CAP],Sold[L. BROKER],"*Fenn*") | G13: =D13/Sold[[#Totals],[DATE]] | I13: SVN | J13: =SUMIFS(Sold[SOLD PRICE],Sold[L. BROKER],"*SVN*")+SUMIFS(Sold[SOLD PRICE],Sold[P. BROKER],"*SVN*") | K13: =COUNTIFS(Sold[L. BROKER],"*SVN*")+COUNTIFS(Sold[P. BROKER],"*SVN*") | L13: =J13/K13 | M13: =AVERAGEIFS(Sold[SOLD CAP],Sold[L. BROKER],"*SVN*") | N13: =K13/Sold[[#Totals],[DATE]]
B14: Tim Strange | C14: =SUMIFS(Sold[SOLD PRICE],Sold[L. BROKER],"*Strange*")+SUMIFS(Sold[SOLD PRICE],Sold[P. BROKER],"*Strange*") | D14: =COUNTIFS(Sold[L. BROKER],"*Strange*")+COUNTIFS(Sold[P. BROKER],"*Strange*") | E14: =C14/D14 | F14: =AVERAGE((AVERAGEIFS(Sold[SOLD CAP],Sold[L. BROKER],"*Strange*")),(AVERAGEIFS(Sold[SOLD CAP],Sold[P. BROKER],"*Strange*"))) | G14: =D14/Sold[[#Totals],[DATE]] | I14: Avison Young | J14: =SUMIFS(Sold[SOLD PRICE],Sold[L. BROKER],"*AY;*")+SUMIFS(Sold[SOLD PRICE],Sold[P. BROKER],"*AY;*") | K14: =COUNTIFS(Sold[L. BROKER],"*AY;*")+COUNTIFS(Sold[P. BROKER],"*AY;*") | L14: =J14/K14 | M14: =AVERAGEIFS(Sold[SOLD CAP],Sold[L. BROKER],"*AY;*") | N14: =K14/Sold[[#Totals],[DATE]]
B15: James Molloy | C15: =SUMIFS(Sold[SOLD PRICE],Sold[L. BROKER],"*Molloy*")+SUMIFS(Sold[SOLD PRICE],Sold[P. BROKER],"*Molloy*") | D15: =COUNTIFS(Sold[L. BROKER],"*Molloy*")+COUNTIFS(Sold[P. BROKER],"*Molloy*") | E15: =C15/D15 | F15: =AVERAGEIFS(Sold[SOLD CAP],Sold[L. BROKER],"*Molloy*") | G15: =D15/Sold[[#Totals],[DATE]] | I15: Avery Postal | J15: =SUMIFS(Sold[SOLD PRICE],Sold[L. BROKER],"*Avery*")+SUMIFS(Sold[SOLD PRICE],Sold[P. BROKER],"*Avery*") | K15: =COUNTIFS(Sold[L. BROKER],"*Avery*")+COUNTIFS(Sold[P. BROKER],"*Avery*") | L15: =J15/K15 | M15: =AVERAGEIFS(Sold[SOLD CAP],Sold[L. BROKER],"*Avery*") | N15: =K15/Sold[[#Totals],[DATE]]
B16: Marc Rampulla | C16: =SUMIFS(Sold[SOLD PRICE],Sold[L. BROKER],"*Rampulla*")+SUMIFS(Sold[SOLD PRICE],Sold[P. BROKER],"*Rampulla*") | D16: =COUNTIFS(Sold[L. BROKER],"*Rampulla*")+COUNTIFS(Sold[P. BROKER],"*Rampulla*") | E16: =C16/D16 | F16: =AVERAGEIFS(Sold[SOLD CAP],Sold[L. BROKER],"*Rampulla*") | G16: =D16/Sold[[#Totals],[DATE]] | I16: Bull Realty | J16: =SUMIFS(Sold[SOLD PRICE],Sold[L. BROKER],"*BR;*")+SUMIFS(Sold[SOLD PRICE],Sold[P. BROKER],"*BR;*") | K16: =COUNTIFS(Sold[L. BROKER],"*BR;*")+COUNTIFS(Sold[P. BROKER],"*BR;*") | L16: =J16/K16 | M16: =AVERAGEIFS(Sold[SOLD CAP],Sold[L. BROKER],"*BR;*") | N16: =K16/Sold[[#Totals],[DATE]]
I17: Sands | J17: =SUMIFS(Sold[SOLD PRICE],Sold[L. BROKER],"*SIG*")+SUMIFS(Sold[SOLD PRICE],Sold[P. BROKER],"*SIG*") | K17: =COUNTIFS(Sold[L. BROKER],"*SIG*")+COUNTIFS(Sold[P. BROKER],"*SIG*") | L17: =J17/K17 | M17: =AVERAGEIFS(Sold[SOLD CAP],Sold[L. BROKER],"*SIG*") | N17: =K17/Sold[[#Totals],[DATE]]
I18: Matthews | J18: =SUMIFS(Sold[SOLD PRICE],Sold[L. BROKER],"*Matthews*")+SUMIFS(Sold[SOLD PRICE],Sold[P. BROKER],"*Matthews*") | K18: =COUNTIFS(Sold[L. BROKER],"*Matthews*")+COUNTIFS(Sold[P. BROKER],"*Matthews*") | L18: =J18/K18 | M18: =AVERAGEIFS(Sold[SOLD CAP],Sold[L. BROKER],"*Matthews*") | N18: =K18/Sold[[#Totals],[DATE]]
I19: SRS | J19: =SUMIFS(Sold[SOLD PRICE],Sold[L. BROKER],"*SRS*")+SUMIFS(Sold[SOLD PRICE],Sold[P. BROKER],"*SRS*") | K19: =COUNTIFS(Sold[L. BROKER],"*SRS*")+COUNTIFS(Sold[P. BROKER],"*SRS*") | L19: =J19/K19 | M19: =AVERAGEIFS(Sold[SOLD CAP],Sold[L. BROKER],"*SRS*") | N19: =K19/Sold[[#Totals],[DATE]]
B21: TTM | C21: 45382 | D21: =C21-366 | I21: TTM | J21: =C21 | K21: =D21
B22: Broker | C22: Volume | D22: Deal Count | E22: Avg. Size | F22: Avg. Cap | G22: Market Share | I22: Firm | J22: Volume | K22: Deal Count | L22: Avg. Size | M22: Avg. Cap | N22: Market Share
B23: Geoff Ficke | C23: =SUMIFS(Sold[SOLD PRICE],Sold[L. BROKER],"*ficke*",Sold[DATE],"<="&$C$21,Sold[DATE],">"&$D$21)+SUMIFS(Sold[SOLD PRICE],Sold[P. BROKER],"*ficke*",Sold[DATE],"<="&$C$21,Sold[DATE],">"&$D$21) | D23: =COUNTIFS(Sold[L. BROKER],"*ficke*",Sold[DATE],"<="&$C$21,Sold[DATE],">"&$D$21)+COUNTIFS(Sold[P. BROKER],"*ficke*",Sold[DATE],"<="&$C$21,Sold[DATE],">"&$D$21) | E23: =C23/D23 | F23: =(AVERAGEIFS(Sold[SOLD CAP],Sold[L. BROKER],"*Ficke*",Sold[DATE],">"&D20,Sold[DATE],"<="&C20)) | G23: =D23/'All Charts'!$BS$92 | I23: SJC | J23: =SUMIFS(Sold[SOLD PRICE],Sold[L. BROKER],"*SJC*",Sold[DATE],">="&$K$21,Sold[DATE],"<="&$J$21)+SUMIFS(Sold[SOLD PRICE],Sold[P. BROKER],"*sjc*",Sold[DATE],">="&$K$21,Sold[DATE],"<="&$J$21) | K23: =COUNTIFS(Sold[L. BROKER],"*sjc*",Sold[DATE],">="&$K$21,Sold[DATE],"<="&$J$21)+COUNTIFS(Sold[P. BROKER],"*sjc*",Sold[DATE],">="&$K$21,Sold[DATE],"<="&$J$21) | L23: =J23/K23 | M23: =AVERAGEIFS(Sold[SOLD CAP],Sold[L. BROKER],"*SJC*",Sold[DATE],">="&$K$21,Sold[DATE],"<="&$J$21) | N23: =K23/'All Charts'!$BS$92
B24: Travis Trautvetter | C24: =SUMIFS(Sold[SOLD PRICE],Sold[L. BROKER],"*traut*",Sold[DATE],"<="&$C$21,Sold[DATE],">"&$D$21)+SUMIFS(Sold[SOLD PRICE],Sold[P. BROKER],"*traut*",Sold[DATE],"<="&$C$21,Sold[DATE],">"&$D$21) | D24: =COUNTIFS(Sold[L. BROKER],"*Traut*",Sold[DATE],"<="&$C$21,Sold[DATE],">"&$D$21)+COUNTIFS(Sold[P. BROKER],"*traut*",Sold[DATE],"<="&$C$21,Sold[DATE],">"&$D$21) | E24: =C24/D24 | F24: =(AVERAGEIFS(Sold[SOLD CAP],Sold[L. BROKER],"*Traut*",Sold[DATE],">"&D22,Sold[DATE],"<="&C22)) | G24: =D24/'All Charts'!$BS$92 | I24: C&W | J24: =SUMIFS(Sold[SOLD PRICE],Sold[L. BROKER],"*C&W*",Sold[DATE],">="&$K$21,Sold[DATE],"<="&$J$21)+SUMIFS(Sold[SOLD PRICE],Sold[P. BROKER],"*C&W*",Sold[DATE],">="&$K$21,Sold[DATE],"<="&$J$21) | K24: =COUNTIFS(Sold[L. BROKER],"*C&W*",Sold[DATE],">="&$K$21,Sold[DATE],"<="&$J$21)+COUNTIFS(Sold[P. BROKER],"*C&W*",Sold[DATE],">="&$K$21,Sold[DATE],"<="&$J$21) | L24: =J24/K24 | M24: =AVERAGEIFS(Sold[SOLD CAP],Sold[L. BROKER],"*C&W*",Sold[DATE],">="&$K$21,Sold[DATE],"<="&$J$21) | N24: =K24/'All Charts'!$BS$92
B25: Scott Briggs | C25: =SUMIFS(Sold[SOLD PRICE],Sold[L. BROKER],"*briggs*",Sold[DATE],"<="&$C$21,Sold[DATE],">"&$D$21)+SUMIFS(Sold[SOLD PRICE],Sold[P. BROKER],"*briggs*",Sold[DATE],"<="&$C$21,Sold[DATE],">"&$D$21) | D25: =COUNTIFS(Sold[L. BROKER],"*briggs*",Sold[DATE],"<="&$C$21,Sold[DATE],">"&$D$21)+COUNTIFS(Sold[P. BROKER],"*briggs*",Sold[DATE],"<="&$C$21,Sold[DATE],">"&$D$21) | E25: =C25/D25 | F25: =(AVERAGEIFS(Sold[SOLD CAP],Sold[L. BROKER],"*Briggs*",Sold[DATE],">"&D21,Sold[DATE],"<="&C21)) | G25: =D25/'All Charts'!$BS$92 | I25: Colliers | J25: =SUMIFS(Sold[SOLD PRICE],Sold[L. BROKER],"*Colliers*",Sold[DATE],">="&$K$21,Sold[DATE],"<="&$J$21)+SUMIFS(Sold[SOLD PRICE],Sold[P. BROKER],"*Colliers*",Sold[DATE],">="&$K$21,Sold[DATE],"<="&$J$21) | K25: =COUNTIFS(Sold[L. BROKER],"*colliers*",Sold[DATE],">="&$K$21,Sold[DATE],"<="&$J$21)+COUNTIFS(Sold[P. BROKER],"*colliers*",Sold[DATE],">="&$K$21,Sold[DATE],"<="&$J$21) | L25: =J25/K25 | M25: =AVERAGEIFS(Sold[SOLD CAP],Sold[L. BROKER],"*Colliers*",Sold[DATE],">="&$K$21,Sold[DATE],"<="&$J$21) | N25: =K25/'All Charts'!$BS$92
B26: Jamie Harrison | C26: =SUMIFS(Sold[SOLD PRICE],Sold[L. BROKER],"*Harrison*",Sold[DATE],"<="&$C$21,Sold[DATE],">"&$D$21)+SUMIFS(Sold[SOLD PRICE],Sold[P. BROKER],"*Harrison*",Sold[DATE],"<="&$C$21,Sold[DATE],">"&$D$21) | D26: =COUNTIFS(Sold[L. BROKER],"*Harrison*",Sold[DATE],"<="&$C$21,Sold[DATE],">"&$D$21)+COUNTIFS(Sold[P. BROKER],"*Harrison*",Sold[DATE],"<="&$C$21,Sold[DATE],">"&$D$21) | E26: =C26/D26 | F26: =(AVERAGEIFS(Sold[SOLD CAP],Sold[L. BROKER],"*Harrison*",Sold[DATE],">"&D14,Sold[DATE],"<="&C14)) | G26: =D26/'All Charts'!$BS$92 | I26: M&M | J26: =SUMIFS(Sold[SOLD PRICE],Sold[L. BROKER],"*M&M*",Sold[DATE],">="&$K$21,Sold[DATE],"<="&$J$21)+SUMIFS(Sold[SOLD PRICE],Sold[P. BROKER],"*M&M*",Sold[DATE],">="&$K$21,Sold[DATE],"<="&$J$21) | K26: =COUNTIFS(Sold[L. BROKER],"*M&M*",Sold[DATE],">="&$K$21,Sold[DATE],"<="&$J$21)+COUNTIFS(Sold[P. BROKER],"*M&M*",Sold[DATE],">="&$K$21,Sold[DATE],"<="&$J$21) | L26: =J26/K26 | M26: =AVERAGEIFS(Sold[SOLD CAP],Sold[L. BROKER],"*M&M*",Sold[DATE],">="&$K$21,Sold[DATE],"<="&$J$21) | N26: =K26/'All Charts'!$BS$92
B27: Karen Wells | C27: =SUMIFS(Sold[SOLD PRICE],Sold[L. BROKER],"*wells*",Sold[DATE],"<="&$C$21,Sold[DATE],">"&$D$21)+SUMIFS(Sold[SOLD PRICE],Sold[P. BROKER],"*wells*",Sold[DATE],"<="&$C$21,Sold[DATE],">"&$D$21) | D27: =COUNTIFS(Sold[L. BROKER],"*wells*",Sold[DATE],"<="&$C$21,Sold[DATE],">"&$D$21)+COUNTIFS(Sold[P. BROKER],"*wells*",Sold[DATE],"<="&$C$21,Sold[DATE],">"&$D$21) | E27: =C27/D27 | F27: =(AVERAGEIFS(Sold[SOLD CAP],Sold[L. BROKER],"*Wells*",Sold[DATE],">"&D22,Sold[DATE],"<="&C22)) | G27: =D27/'All Charts'!$BS$92 | I27: Capital Pacific | J27: =SUMIFS(Sold[SOLD PRICE],Sold[L. BROKER],"*CP;*",Sold[DATE],">="&$K$21,Sold[DATE],"<="&$J$21)+SUMIFS(Sold[SOLD PRICE],Sold[P. BROKER],"*CP;*",Sold[DATE],">="&$K$21,Sold[DATE],"<="&$J$21) | K27: =COUNTIFS(Sold[L. BROKER],"*CP;*",Sold[DATE],">="&$K$21,Sold[DATE],"<="&$J$21)+COUNTIFS(Sold[P. BROKER],"*cp;*",Sold[DATE],">="&$K$21,Sold[DATE],"<="&$J$21) | L27: =J27/K27 | M27: =AVERAGEIFS(Sold[SOLD CAP],Sold[L. BROKER],"*CP;*",Sold[DATE],">="&$K$21,Sold[DATE],"<="&$J$21) | N27: =K27/'All Charts'!$BS$92
B28: Andy Gallas | C28: =SUMIFS(Sold[SOLD PRICE],Sold[L. BROKER],"*gallas*",Sold[DATE],"<="&$C$21,Sold[DATE],">"&$D$21)+SUMIFS(Sold[SOLD PRICE],Sold[P. BROKER],"*gallas*",Sold[DATE],"<="&$C$21,Sold[DATE],">"&$D$21) | D28: =COUNTIFS(Sold[L. BROKER],"*gallas*",Sold[DATE],"<="&$C$21,Sold[DATE],">"&$D$21)+COUNTIFS(Sold[P. BROKER],"*gallas*",Sold[DATE],"<="&$C$21,Sold[DATE],">"&$D$21) | E28: =C28/D28 | F28: =(AVERAGEIFS(Sold[SOLD CAP],Sold[L. BROKER],"*Gallas*",Sold[DATE],">"&D22,Sold[DATE],"<="&C22)) | G28: =D28/'All Charts'!$BS$92 | I28: CBRE | J28: =SUMIFS(Sold[SOLD PRICE],Sold[L. BROKER],"*CBRE*",Sold[DATE],">="&$K$21,Sold[DATE],"<="&$J$21)+SUMIFS(Sold[SOLD PRICE],Sold[P. BROKER],"*CBRE*",Sold[DATE],">="&$K$21,Sold[DATE],"<="&$J$21) | K28: =COUNTIFS(Sold[L. BROKER],"*CBRE*",Sold[DATE],">="&$K$21,Sold[DATE],"<="&$J$21)+COUNTIFS(Sold[P. BROKER],"*cbre*",Sold[DATE],">="&$K$21,Sold[DATE],"<="&$J$21) | L28: =J28/K28 | M28: =AVERAGEIFS(Sold[SOLD CAP],Sold[L. BROKER],"*CBRE*",Sold[DATE],">="&$K$21,Sold[DATE],"<="&$J$21) | N28: =K28/'All Charts'!$BS$92
B29: Alex Mobin | C29: =SUMIFS(Sold[SOLD PRICE],Sold[L. BROKER],"*Mobin*",Sold[DATE],"<="&$C$21,Sold[DATE],">"&$D$21)+SUMIFS(Sold[SOLD PRICE],Sold[P. BROKER],"*Mobin*",Sold[DATE],"<="&$C$21,Sold[DATE],">"&$D$21) | D29: =COUNTIFS(Sold[L. BROKER],"*Mobin*",Sold[DATE],"<="&$C$21,Sold[DATE],">"&$D$21)+COUNTIFS(Sold[P. BROKER],"*Mobin*",Sold[DATE],"<="&$C$21,Sold[DATE],">"&$D$21) | E29: =C29/D29 | F29: =(AVERAGEIFS(Sold[SOLD CAP],Sold[L. BROKER],"*Mobin*",Sold[DATE],">"&D18,Sold[DATE],"<="&C18)) | G29: =D29/'All Charts'!$BS$92 | I29: Newmark | J29: =SUMIFS(Sold[SOLD PRICE],Sold[L. BROKER],"*Newmark*",Sold[DATE],">="&$K$21,Sold[DATE],"<="&$J$21)+SUMIFS(Sold[SOLD PRICE],Sold[P. BROKER],"*Newmark*",Sold[DATE],">="&$K$21,Sold[DATE],"<="&$J$21) | K29: =COUNTIFS(Sold[L. BROKER],"*newmark*",Sold[DATE],">="&$K$21,Sold[DATE],"<="&$J$21)+COUNTIFS(Sold[P. BROKER],"*newmark*",Sold[DATE],">="&$K$21,Sold[DATE],"<="&$J$21) | L29: =J29/K29 | M29: =AVERAGEIFS(Sold[SOLD CAP],Sold[L. BROKER],"*Newmark*",Sold[DATE],">="&$K$21,Sold[DATE],"<="&$J$21) | N29: =K29/'All Charts'!$BS$92
B30: Justin Fenn | C30: =SUMIFS(Sold[SOLD PRICE],Sold[L. BROKER],"*fenn*",Sold[DATE],"<="&$C$21,Sold[DATE],">"&$D$21)+SUMIFS(Sold[SOLD PRICE],Sold[P. BROKER],"*fenn*",Sold[DATE],"<="&$C$21,Sold[DATE],">"&$D$21) | D30: =COUNTIFS(Sold[L. BROKER],"*fenn*",Sold[DATE],"<="&$C$21,Sold[DATE],">"&$D$21)+COUNTIFS(Sold[P. BROKER],"*fenn*",Sold[DATE],"<="&$C$21,Sold[DATE],">"&$D$21) | E30: =C30/D30 | F30: =(AVERAGEIFS(Sold[SOLD CAP],Sold[L. BROKER],"*Fenn*",Sold[DATE],">"&D23,Sold[DATE],"<="&C23)) | G30: =D30/'All Charts'!$BS$92 | I30: Touchstone | J30: =SUMIFS(Sold[SOLD PRICE],Sold[L. BROKER],"*TCP*",Sold[DATE],">="&$K$21,Sold[DATE],"<="&$J$21)+SUMIFS(Sold[SOLD PRICE],Sold[P. BROKER],"*TCP*",Sold[DATE],">="&$K$21,Sold[DATE],"<="&$J$21) | K30: =COUNTIFS(Sold[L. BROKER],"*TCP*",Sold[DATE],">="&$K$21,Sold[DATE],"<="&$J$21)+COUNTIFS(Sold[P. BROKER],"*TCP*",Sold[DATE],">="&$K$21,Sold[DATE],"<="&$J$21) | L30: =J30/K30 | M30: =AVERAGEIFS(Sold[SOLD CAP],Sold[L. BROKER],"*TCP*",Sold[DATE],">="&$K$21,Sold[DATE],"<="&$J$21) | N30: =K30/'All Charts'!$BS$92
B31: Bob Cottle | C31: =SUMIFS(Sold[SOLD PRICE],Sold[L. BROKER],"*Cottle*",Sold[DATE],"<="&$C$21,Sold[DATE],">"&$D$21)+SUMIFS(Sold[SOLD PRICE],Sold[P. BROKER],"*Cottle*",Sold[DATE],"<="&$C$21,Sold[DATE],">"&$D$21) | D31: =COUNTIFS(Sold[L. BROKER],"*Cottle*",Sold[DATE],"<="&$C$21,Sold[DATE],">"&$D$21)+COUNTIFS(Sold[P. BROKER],"*Cottle*",Sold[DATE],"<="&$C$21,Sold[DATE],">"&$D$21) | E31: =C31/D31 | F31: =(AVERAGEIFS(Sold[SOLD CAP],Sold[L. BROKER],"*Cottle*",Sold[DATE],">"&D23,Sold[DATE],"<="&C23)) | G31: =D31/'All Charts'!$BS$92 | I31: Bear Wells | J31: =SUMIFS(Sold[SOLD PRICE],Sold[L. BROKER],"*BW;*",Sold[DATE],">="&$K$21,Sold[DATE],"<="&$J$21)+SUMIFS(Sold[SOLD PRICE],Sold[P. BROKER],"*BW;*",Sold[DATE],">="&$K$21,Sold[DATE],"<="&$J$21) | K31: =COUNTIFS(Sold[L. BROKER],"*bw;*",Sold[DATE],">="&$K$21,Sold[DATE],"<="&$J$21)+COUNTIFS(Sold[P. BROKER],"*bw;*",Sold[DATE],">="&$K$21,Sold[DATE],"<="&$J$21) | L31: =J31/K31 | M31: =AVERAGEIFS(Sold[SOLD CAP],Sold[L. BROKER],"*BW;*",Sold[DATE],">="&$K$21,Sold[DATE],"<="&$J$21) | N31: =K31/'All Charts'!$BS$92
B32: Darrin Kennedy | C32: =SUMIFS(Sold[SOLD PRICE],Sold[L. BROKER],"*Kennedy*",Sold[DATE],"<="&$C$21,Sold[DATE],">"&$D$21)+SUMIFS(Sold[SOLD PRICE],Sold[P. BROKER],"*Kennedy*",Sold[DATE],"<="&$C$21,Sold[DATE],">"&$D$21) | D32: =COUNTIFS(Sold[L. BROKER],"*Kennedy*",Sold[DATE],"<="&$C$21,Sold[DATE],">"&$D$21)+COUNTIFS(Sold[P. BROKER],"*Kennedy*",Sold[DATE],"<="&$C$21,Sold[DATE],">"&$D$21) | E32: =C32/D32 | F32: =(AVERAGEIFS(Sold[SOLD CAP],Sold[L. BROKER],"*Kennedy*",Sold[DATE],">"&D23,Sold[DATE],"<="&C23)) | G32: =D32/'All Charts'!$BS$92 | I32: Bull Realty | J32: =SUMIFS(Sold[SOLD PRICE],Sold[L. BROKER],"*BR;*",Sold[DATE],">="&$K$21,Sold[DATE],"<="&$J$21)+SUMIFS(Sold[SOLD PRICE],Sold[P. BROKER],"*BR;*",Sold[DATE],">="&$K$21,Sold[DATE],"<="&$J$21) | K32: =COUNTIFS(Sold[L. BROKER],"*br;*",Sold[DATE],">="&$K$21,Sold[DATE],"<="&$J$21)+COUNTIFS(Sold[P. BROKER],"*br;*",Sold[DATE],">="&$K$21,Sold[DATE],"<="&$J$21) | L32: =J32/K32 | M32: =AVERAGEIFS(Sold[SOLD CAP],Sold[L. BROKER],"*BR;*",Sold[DATE],">="&$K$21,Sold[DATE],"<="&$J$21) | N32: =K32/'All Charts'!$BS$92
B33: Tim Strange | C33: =SUMIFS(Sold[SOLD PRICE],Sold[L. BROKER],"*Strange*",Sold[DATE],"<="&$C$21,Sold[DATE],">"&$D$21)+SUMIFS(Sold[SOLD PRICE],Sold[P. BROKER],"*Strange*",Sold[DATE],"<="&$C$21,Sold[DATE],">"&$D$21) | D33: =COUNTIFS(Sold[L. BROKER],"*Strange*",Sold[DATE],"<="&$C$21,Sold[DATE],">"&$D$21)+COUNTIFS(Sold[P. BROKER],"*Strange*",Sold[DATE],"<="&$C$21,Sold[DATE],">"&$D$21) | E33: =C33/D33 | F33: =(AVERAGEIFS(Sold[SOLD CAP],Sold[L. BROKER],"*Strange*",Sold[DATE],">"&D23,Sold[DATE],"<="&C23)) | G33: =D33/'All Charts'!$BS$92 | I33: JLL | J33: =SUMIFS(Sold[SOLD PRICE],Sold[L. BROKER],"*JLL*",Sold[DATE],">="&$K$21,Sold[DATE],"<="&$J$21)+SUMIFS(Sold[SOLD PRICE],Sold[P. BROKER],"*JLL*",Sold[DATE],">="&$K$21,Sold[DATE],"<="&$J$21) | K33: =COUNTIFS(Sold[L. BROKER],"*jll*",Sold[DATE],">="&$K$21,Sold[DATE],"<="&$J$21)+COUNTIFS(Sold[P. BROKER],"*jll*",Sold[DATE],">="&$K$21,Sold[DATE],"<="&$J$21) | L33: =J33/K33 | M33: =AVERAGEIFS(Sold[SOLD CAP],Sold[L. BROKER],"*JLL*",Sold[DATE],">="&$K$21,Sold[DATE],"<="&$J$21) | N33: =K33/'All Charts'!$BS$92
I34: SVN | J34: =SUMIFS(Sold[SOLD PRICE],Sold[L. BROKER],"*SVN*",Sold[DATE],">="&$K$21,Sold[DATE],"<="&$J$21)+SUMIFS(Sold[SOLD PRICE],Sold[P. BROKER],"*SVN*",Sold[DATE],">="&$K$21,Sold[DATE],"<="&$J$21) | K34: =COUNTIFS(Sold[L. BROKER],"*SVN*",Sold[DATE],">="&$K$21,Sold[DATE],"<="&$J$21)+COUNTIFS(Sold[P. BROKER],"*SVN*",Sold[DATE],">="&$K$21,Sold[DATE],"<="&$J$21) | L34: =J34/K34 | M34: =AVERAGEIFS(Sold[SOLD CAP],Sold[L. BROKER],"*SVN*",Sold[DATE],">="&$K$21,Sold[DATE],"<="&$J$21) | N34: =K34/'All Charts'!$BS$92
I35: Avison Young | J35: =SUMIFS(Sold[SOLD PRICE],Sold[L. BROKER],"*ay;*",Sold[DATE],">="&$K$21,Sold[DATE],"<="&$J$21)+SUMIFS(Sold[SOLD PRICE],Sold[P. BROKER],"*ay;*",Sold[DATE],">="&$K$21,Sold[DATE],"<="&$J$21) | K35: =COUNTIFS(Sold[L. BROKER],"*ay;*",Sold[DATE],">="&$K$21,Sold[DATE],"<="&$J$21)+COUNTIFS(Sold[P. BROKER],"*ay;*",Sold[DATE],">="&$K$21,Sold[DATE],"<="&$J$21) | L35: =J35/K35 | M35: =AVERAGEIFS(Sold[SOLD CAP],Sold[L. BROKER],"*ay;*",Sold[DATE],">="&$K$21,Sold[DATE],"<="&$J$21) | N35: =K35/'All Charts'!$BS$92
I36: Avery Postal | J36: =SUMIFS(Sold[SOLD PRICE],Sold[L. BROKER],"*Avery*",Sold[DATE],">="&$K$21,Sold[DATE],"<="&$J$21)+SUMIFS(Sold[SOLD PRICE],Sold[P. BROKER],"*Avery*",Sold[DATE],">="&$K$21,Sold[DATE],"<="&$J$21) | K36: =COUNTIFS(Sold[L. BROKER],"*avery*",Sold[DATE],">="&$K$21,Sold[DATE],"<="&$J$21)+COUNTIFS(Sold[P. BROKER],"*avery*",Sold[DATE],">="&$K$21,Sold[DATE],"<="&$J$21) | L36: =J36/K36 | M36: =AVERAGEIFS(Sold[SOLD CAP],Sold[L. BROKER],"*avery*",Sold[DATE],">="&$K$21,Sold[DATE],"<="&$J$21) | N36: =K36/'All Charts'!$BS$92
I37: Sands | J37: =SUMIFS(Sold[SOLD PRICE],Sold[L. BROKER],"*SIG;*",Sold[DATE],">="&$K$21,Sold[DATE],"<="&$J$21)+SUMIFS(Sold[SOLD PRICE],Sold[P. BROKER],"*SIG*",Sold[DATE],">="&$K$21,Sold[DATE],"<="&$J$21) | K37: =COUNTIFS(Sold[L. BROKER],"*sig;*",Sold[DATE],">="&$K$21,Sold[DATE],"<="&$J$21)+COUNTIFS(Sold[P. BROKER],"*sig;*",Sold[DATE],">="&$K$21,Sold[DATE],"<="&$J$21) | L37: =J37/K37 | M37: =AVERAGEIFS(Sold[SOLD CAP],Sold[L. BROKER],"*SIG;*",Sold[DATE],">="&$K$21,Sold[DATE],"<="&$J$21) | N37: =K37/'All Charts'!$BS$92
I38: Matthews | J38: =SUMIFS(Sold[SOLD PRICE],Sold[L. BROKER],"*Matthews*",Sold[DATE],">="&$K$21,Sold[DATE],"<="&$J$21)+SUMIFS(Sold[SOLD PRICE],Sold[P. BROKER],"*Matthews*",Sold[DATE],">="&$K$21,Sold[DATE],"<="&$J$21) | K38: =COUNTIFS(Sold[L. BROKER],"*matthews*",Sold[DATE],">="&$K$21,Sold[DATE],"<="&$J$21)+COUNTIFS(Sold[P. BROKER],"*matthews**",Sold[DATE],">="&$K$21,Sold[DATE],"<="&$J$21) | L38: =J38/K38 | M38: =AVERAGEIFS(Sold[SOLD CAP],Sold[L. BROKER],"*matthews*",Sold[DATE],">="&$K$21,Sold[DATE],"<="&$J$21) | N38: =K38/'All Charts'!$BS$92
I39: SRS | J39: =SUMIFS(Sold[SOLD PRICE],Sold[L. BROKER],"*SRS*",Sold[DATE],">="&$K$21,Sold[DATE],"<="&$J$21)+SUMIFS(Sold[SOLD PRICE],Sold[P. BROKER],"*SRS*",Sold[DATE],">="&$K$21,Sold[DATE],"<="&$J$21) | K39: =COUNTIFS(Sold[L. BROKER],"*srs*",Sold[DATE],">="&$K$21,Sold[DATE],"<="&$J$21)+COUNTIFS(Sold[P. BROKER],"*srs*",Sold[DATE],">="&$K$21,Sold[DATE],"<="&$J$21) | L39: =J39/K39 | M39: =AVERAGEIFS(Sold[SOLD CAP],Sold[L. BROKER],"*srs*",Sold[DATE],">="&$K$21,Sold[DATE],"<="&$J$21) | N39: =K39/'All Charts'!$BS$92

Sheet FRPP-Leased
B1: 1 | C1: =B1+1 | D1: =C1+1 | E1: =D1+1 | F1: =E1+1 | G1: =F1+1 | H1: =G1+1 | I1: =H1+1 | J1: =I1+1 | ... DJ1: =DI1+1
B2: Real Property Unique Identifier | C2: Reporting Agency | D2: Reporting Agency Code | E2: Reporting Bureau | F2: Reporting Bureau Code | G2: Using Agency | H2: Using Agency Code | I2: Using Bureau | J2: Using Bureau Code | K2: US/Foreign | L2: Country Code | M2: Country Name | N2: State Code | O2: State Name | P2: County Code | Q2: County Name | R2: City Code | S2: City Name | T2: Zip Code | U2: Core-based Statistical Area | V2: Core-based Statistical Area Code | W2: Street Address | X2: Installation Id | Y2: Installation Name | Z2: Sub Installation Id | AA2: Latitude | AB2: Longitude | AC2: Legal Interest Indicator | AD2: Legal Interest Code | AE2: Real Property Type | AF2: Real Property Type Code | AG2: Real Property Use | AH2: Real Property Use Code | AI2: Utilization | AJ2: Utilization Code | AK2: Asset Status | AL2: Asset Status Code | AM2: Historical Status | AN2: Historical Status Code | AO2: Field Office | AP2: Field Office Code | AQ2: Field Office Collocation | AR2: Field Office Collocation Code | AS2: Acres | AT2: Actual Sales Price | AU2: Building Age | AV2: Reason Cannot Currently Be Disposed | AW2: Reason Cannot Currently Be Disposed Code | AX2: Cannot Currently Be Disposed of Date | AY2: CFO Agency | AZ2: Congressional District | BA2: Consecutive Years Underutilized | BB2: Date Start of Underutilized | BC2: Determination to Dispose Date | BD2: Determine # of Contractors | BE2: Determine Number of Fed Contractors Code | BF2: Number of Federal Contractors | BG2: Determine # of Employees | BH2: Determine Number of Fed Employees Code | BI2: Number of Federal Employees | BJ2: Disposition Date | BK2: Disposition Method | BL2: Disposition Method Code | BM2: Estimated Future Capital Expenditures | BN2: Estimated Net Present Value | BO2: Excess Date | BP2: FASTA Disposal Exclusion | BQ2: FASTA Disposal Exclusion Code | BR2: FASTA Disposal Exclusion Reason | BS2: FASTA Disposal Exclusion Reason Code | BT2: FiscalYear | BU2: Historical Capital Expenditures | BV2: Lease Annual Rent to Lessor | BW2: Leased Annual Maintenance Costs | BX2: Leased Annual Operations Costs | BY2: Lease Authority | BZ2: Lease Authority Code | CA2: Lease Expiration Date | CB2: Lease Occupancy Date | CC2: Lease Start Date | CD2: Net Proceeds | CE2: Number of Days Excess | CF2: Number of Days Surplus | CG2: Number of Days Underutilized | CH2: Outgrant Indicator | CI2: Owned and Otherwise Managed Annual Operations Cost | CJ2: Owned and Otherwise Managed Annual Maintenance Cost | CK2: Repair Needs | CL2: Replacement Value | CM2: Condition Index | CN2: Report of Excess Accepted Date | CO2: Report of Excess Submitted Date | CP2: Reduce the Footprint | CQ2: Square Feet (Buildings) | CR2: Square Feet Unit of Measure | CS2: SquareFeet UnitOfMeasure Code | CT2: Structural Units | CU2: Surplus Declaration Date | CV2: Sustainability | CW2: Sustainability Code | CX2: Unit Of Measure | CY2: Unit Of Measure Code | CZ2: Year Asset Reported Underutilized | DA2: Year of Construction | DB2: Outgrant Indicator Value | DC2: Asset Height Range | DD2: Asset Height | DE2: Asset Height Range Above Mean Sea Level | DF2: Asset Height Above Mean Sea Level | DG2: Elevation Above Mean Sea Level | DH2: FOIA Exemption | DI2: FOIA Exemption Code | DJ2: Statutory Citation
